{
  "versionA": "1.18.2",
  "versionB": "1.19",
  "packagesAdded": [
    "io.papermc.paper.annotation",
    "org.bukkit.generator.structure"
  ],
  "packagesRemoved": [],
  "packagesChanged": [
    "com.destroystokyo.paper",
    "com.destroystokyo.paper.block",
    "com.destroystokyo.paper.entity",
    "com.destroystokyo.paper.entity.ai",
    "com.destroystokyo.paper.entity.villager",
    "com.destroystokyo.paper.event.block",
    "com.destroystokyo.paper.event.entity",
    "com.destroystokyo.paper.event.executor",
    "com.destroystokyo.paper.event.executor.asm",
    "com.destroystokyo.paper.event.inventory",
    "com.destroystokyo.paper.event.player",
    "com.destroystokyo.paper.event.profile",
    "com.destroystokyo.paper.event.server",
    "com.destroystokyo.paper.exception",
    "com.destroystokyo.paper.inventory",
    "com.destroystokyo.paper.inventory.meta",
    "com.destroystokyo.paper.loottable",
    "com.destroystokyo.paper.network",
    "com.destroystokyo.paper.profile",
    "com.destroystokyo.paper.util",
    "com.destroystokyo.paper.utils",
    "io.papermc.paper.advancement",
    "io.papermc.paper.chat",
    "io.papermc.paper.command",
    "io.papermc.paper.datapack",
    "io.papermc.paper.enchantments",
    "io.papermc.paper.entity",
    "io.papermc.paper.event.block",
    "io.papermc.paper.event.entity",
    "io.papermc.paper.event.packet",
    "io.papermc.paper.event.player",
    "io.papermc.paper.event.server",
    "io.papermc.paper.event.world",
    "io.papermc.paper.event.world.border",
    "io.papermc.paper.inventory",
    "io.papermc.paper.potion",
    "io.papermc.paper.registry",
    "io.papermc.paper.tag",
    "io.papermc.paper.text",
    "io.papermc.paper.util",
    "io.papermc.paper.world",
    "io.papermc.paper.world.structure",
    "org.bukkit",
    "org.bukkit.advancement",
    "org.bukkit.attribute",
    "org.bukkit.block",
    "org.bukkit.block.banner",
    "org.bukkit.block.data",
    "org.bukkit.block.data.type",
    "org.bukkit.block.structure",
    "org.bukkit.boss",
    "org.bukkit.command",
    "org.bukkit.command.defaults",
    "org.bukkit.configuration",
    "org.bukkit.configuration.file",
    "org.bukkit.configuration.serialization",
    "org.bukkit.conversations",
    "org.bukkit.enchantments",
    "org.bukkit.entity",
    "org.bukkit.entity.memory",
    "org.bukkit.entity.minecart",
    "org.bukkit.event",
    "org.bukkit.event.block",
    "org.bukkit.event.command",
    "org.bukkit.event.enchantment",
    "org.bukkit.event.entity",
    "org.bukkit.event.hanging",
    "org.bukkit.event.inventory",
    "org.bukkit.event.player",
    "org.bukkit.event.raid",
    "org.bukkit.event.server",
    "org.bukkit.event.vehicle",
    "org.bukkit.event.weather",
    "org.bukkit.event.world",
    "org.bukkit.generator",
    "org.bukkit.help",
    "org.bukkit.inventory",
    "org.bukkit.inventory.meta",
    "org.bukkit.inventory.meta.tags",
    "org.bukkit.loot",
    "org.bukkit.map",
    "org.bukkit.material",
    "org.bukkit.material.types",
    "org.bukkit.metadata",
    "org.bukkit.permissions",
    "org.bukkit.persistence",
    "org.bukkit.plugin",
    "org.bukkit.plugin.java",
    "org.bukkit.plugin.messaging",
    "org.bukkit.potion",
    "org.bukkit.profile",
    "org.bukkit.projectiles",
    "org.bukkit.scheduler",
    "org.bukkit.scoreboard",
    "org.bukkit.structure",
    "org.bukkit.util",
    "org.bukkit.util.io",
    "org.bukkit.util.noise",
    "org.bukkit.util.permissions",
    "org.spigotmc",
    "org.spigotmc.event.entity",
    "org.spigotmc.event.player"
  ],
  "classesAdded": [
    "io.papermc.paper.entity.LookAnchor",
    "io.papermc.paper.entity.RelativeTeleportFlag",
    "io.papermc.paper.event.entity.EntityPortalReadyEvent",
    "io.papermc.paper.event.entity.WardenAngerChangeEvent",
    "org.bukkit.block.BlockSupport",
    "org.bukkit.block.SculkCatalyst",
    "org.bukkit.block.SculkShrieker",
    "org.bukkit.block.data.Hangable",
    "org.bukkit.block.data.type.Barrel",
    "org.bukkit.block.data.type.MangrovePropagule",
    "org.bukkit.block.data.type.SculkCatalyst",
    "org.bukkit.block.data.type.SculkShrieker",
    "org.bukkit.block.data.type.SculkVein",
    "org.bukkit.entity.Allay",
    "org.bukkit.entity.Boat.Status",
    "org.bukkit.entity.Boat.Type",
    "org.bukkit.entity.ChestBoat",
    "org.bukkit.entity.Frog",
    "org.bukkit.entity.Frog.Variant",
    "org.bukkit.entity.Tadpole",
    "org.bukkit.entity.Warden",
    "org.bukkit.generator.structure.Structure",
    "org.bukkit.generator.structure.StructureType",
    "org.bukkit.map.MapPalette.MapColorCache",
    "org.bukkit.util.StructureSearchResult"
  ],
  "classesRemoved": [],
  "classesChanged": [
    "com.destroystokyo.paper.event.server.PaperServerListPingEvent",
    "com.destroystokyo.paper.profile.PlayerProfile",
    "org.bukkit.Art",
    "org.bukkit.Bukkit",
    "org.bukkit.GameEvent",
    "org.bukkit.GameRule",
    "org.bukkit.Material",
    "org.bukkit.OfflinePlayer",
    "org.bukkit.Particle",
    "org.bukkit.Registry",
    "org.bukkit.Server",
    "org.bukkit.Sound",
    "org.bukkit.Tag",
    "org.bukkit.TreeType",
    "org.bukkit.Vibration",
    "org.bukkit.World",
    "org.bukkit.block.Biome",
    "org.bukkit.block.data.BlockData",
    "org.bukkit.block.data.type.Lantern",
    "org.bukkit.command.CommandSender",
    "org.bukkit.conversations.BooleanPrompt",
    "org.bukkit.enchantments.Enchantment",
    "org.bukkit.entity.Boat",
    "org.bukkit.entity.Cat.Type",
    "org.bukkit.entity.Entity",
    "org.bukkit.entity.EntityType",
    "org.bukkit.entity.Goat",
    "org.bukkit.entity.HumanEntity",
    "org.bukkit.entity.Panda",
    "org.bukkit.entity.Parrot",
    "org.bukkit.entity.Player",
    "org.bukkit.entity.Pose",
    "org.bukkit.entity.Wolf",
    "org.bukkit.entity.ZombieVillager",
    "org.bukkit.entity.memory.MemoryKey",
    "org.bukkit.event.entity.CreatureSpawnEvent.SpawnReason",
    "org.bukkit.event.entity.EntityDamageEvent.DamageCause",
    "org.bukkit.event.entity.EntityPotionEffectEvent.Cause",
    "org.bukkit.event.entity.EntityTransformEvent.TransformReason",
    "org.bukkit.event.player.PlayerAnimationType",
    "org.bukkit.event.player.PlayerTeleportEvent",
    "org.bukkit.event.server.ServerListPingEvent",
    "org.bukkit.event.world.GenericGameEvent",
    "org.bukkit.event.world.WorldEvent",
    "org.bukkit.loot.LootTables",
    "org.bukkit.map.MapCanvas",
    "org.bukkit.map.MapPalette",
    "org.bukkit.potion.PotionEffectType"
  ],
  "membersAdded": {
    "org.bukkit.event.entity.EntityTransformEvent.TransformReason": [
      "METAMORPHOSIS"
    ],
    "org.bukkit.TreeType": [
      "TALL_MANGROVE"
    ],
    "org.bukkit.enchantments.Enchantment": [
      "SWIFT_SNEAK"
    ],
    "io.papermc.paper.entity.LookAnchor": [
      "EYES",
      "LookAnchor()"
    ],
    "org.bukkit.entity.Player": [
      "lookAt(Entity,LookAnchor,LookAnchor)",
      "lookAt(Location,LookAnchor)",
      "lookAt(double,double,double,LookAnchor)",
      "stopSound(SoundCategory)",
      "teleport(Location,TeleportCause,boolean,boolean,RelativeTeleportFlag...)"
    ],
    "org.bukkit.Art": [
      "EARTH",
      "WIND"
    ],
    "org.bukkit.event.player.PlayerAnimationType": [
      "OFF_ARM_SWING"
    ],
    "io.papermc.paper.event.entity.EntityPortalReadyEvent": [
      "EntityPortalReadyEvent(Entity,World,PortalType)",
      "getTargetWorld()",
      "portalType",
      "setTargetWorld(World)",
      "targetWorld"
    ],
    "org.bukkit.block.Biome": [
      "DEEP_DARK",
      "MANGROVE_SWAMP"
    ],
    "org.bukkit.block.data.type.SculkShrieker": [
      "isCanSummon()",
      "isShrieking()",
      "setCanSummon(boolean)",
      "setShrieking(boolean)"
    ],
    "org.bukkit.map.MapCanvas": [
      "getBasePixelColor(int,int)",
      "getPixelColor(int,int)",
      "setPixelColor(int,int,Color)"
    ],
    "org.bukkit.World": [
      "locateNearestStructure(Location,Structure,int,boolean)"
    ],
    "org.bukkit.Material": [
      "ACACIA_CHEST_BOAT",
      "ALLAY_SPAWN_EGG",
      "BIRCH_CHEST_BOAT",
      "DARK_OAK_CHEST_BOAT",
      "DISC_FRAGMENT_5",
      "ECHO_SHARD",
      "FROGSPAWN",
      "FROG_SPAWN_EGG",
      "GOAT_HORN",
      "JUNGLE_CHEST_BOAT",
      "MANGROVE_BOAT",
      "MANGROVE_BUTTON",
      "MANGROVE_CHEST_BOAT",
      "MANGROVE_DOOR",
      "MANGROVE_FENCE",
      "MANGROVE_FENCE_GATE",
      "MANGROVE_LEAVES",
      "MANGROVE_LOG",
      "MANGROVE_PLANKS",
      "MANGROVE_PRESSURE_PLATE",
      "MANGROVE_PROPAGULE",
      "MANGROVE_ROOTS",
      "MANGROVE_SIGN",
      "MANGROVE_SLAB",
      "MANGROVE_STAIRS",
      "MANGROVE_TRAPDOOR",
      "MANGROVE_WALL_SIGN",
      "MANGROVE_WOOD",
      "MUD",
      "MUDDY_MANGROVE_ROOTS",
      "MUD_BRICKS",
      "MUD_BRICK_SLAB",
      "MUD_BRICK_STAIRS",
      "MUD_BRICK_WALL",
      "OAK_CHEST_BOAT",
      "OCHRE_FROGLIGHT",
      "PACKED_MUD",
      "PEARLESCENT_FROGLIGHT",
      "POTTED_MANGROVE_PROPAGULE",
      "RECOVERY_COMPASS",
      "REINFORCED_DEEPSLATE",
      "SCULK",
      "SCULK_CATALYST",
      "SCULK_SHRIEKER",
      "SCULK_VEIN",
      "SPRUCE_CHEST_BOAT",
      "STRIPPED_MANGROVE_LOG",
      "STRIPPED_MANGROVE_WOOD",
      "TADPOLE_BUCKET",
      "TADPOLE_SPAWN_EGG",
      "VERDANT_FROGLIGHT",
      "WARDEN_SPAWN_EGG"
    ],
    "org.bukkit.entity.Boat": [
      "getBoatType()",
      "setBoatType(Type)"
    ],
    "org.bukkit.event.entity.EntityDamageEvent.DamageCause": [
      "SONIC_BOOM"
    ],
    "org.bukkit.loot.LootTables": [
      "ANCIENT_CITY",
      "ANCIENT_CITY_ICE_BOX"
    ],
    "org.bukkit.command.CommandSender": [
      "sendPlainMessage(String)",
      "sendRichMessage(String)"
    ],
    "org.bukkit.entity.Entity": [
      "teleport(Location,TeleportCause,boolean)",
      "teleport(Location,TeleportCause,boolean,boolean)",
      "teleport(Location,boolean)",
      "teleport(Location,boolean,boolean)"
    ],
    "org.bukkit.block.data.BlockData": [
      "isFaceSturdy(BlockFace,BlockSupport)",
      "isSupported(Block)",
      "isSupported(Location)"
    ],
    "org.bukkit.block.SculkShrieker": [
      "getWarningLevel()",
      "setWarningLevel(int)"
    ],
    "org.bukkit.Sound": [
      "MUSIC_DISC_5",
      "BLOCK_FROGLIGHT_BREAK",
      "BLOCK_FROGLIGHT_FALL",
      "BLOCK_FROGLIGHT_HIT",
      "BLOCK_FROGLIGHT_PLACE",
      "BLOCK_FROGLIGHT_STEP",
      "BLOCK_FROGSPAWN_BREAK",
      "BLOCK_FROGSPAWN_FALL",
      "BLOCK_FROGSPAWN_HATCH",
      "BLOCK_FROGSPAWN_HIT",
      "BLOCK_FROGSPAWN_PLACE",
      "BLOCK_FROGSPAWN_STEP",
      "BLOCK_MANGROVE_ROOTS_BREAK",
      "BLOCK_MANGROVE_ROOTS_FALL",
      "BLOCK_MANGROVE_ROOTS_HIT",
      "BLOCK_MANGROVE_ROOTS_PLACE",
      "BLOCK_MANGROVE_ROOTS_STEP",
      "BLOCK_MUDDY_MANGROVE_ROOTS_BREAK",
      "BLOCK_MUDDY_MANGROVE_ROOTS_FALL",
      "BLOCK_MUDDY_MANGROVE_ROOTS_HIT",
      "BLOCK_MUDDY_MANGROVE_ROOTS_PLACE",
      "BLOCK_MUDDY_MANGROVE_ROOTS_STEP",
      "BLOCK_MUD_BREAK",
      "BLOCK_MUD_BRICKS_BREAK",
      "BLOCK_MUD_BRICKS_FALL",
      "BLOCK_MUD_BRICKS_HIT",
      "BLOCK_MUD_BRICKS_PLACE",
      "BLOCK_MUD_BRICKS_STEP",
      "BLOCK_MUD_FALL",
      "BLOCK_MUD_HIT",
      "BLOCK_MUD_PLACE",
      "BLOCK_MUD_STEP",
      "BLOCK_PACKED_MUD_BREAK",
      "BLOCK_PACKED_MUD_FALL",
      "BLOCK_PACKED_MUD_HIT",
      "BLOCK_PACKED_MUD_PLACE",
      "BLOCK_PACKED_MUD_STEP",
      "BLOCK_SCULK_BREAK",
      "BLOCK_SCULK_CATALYST_BLOOM",
      "BLOCK_SCULK_CATALYST_BREAK",
      "BLOCK_SCULK_CATALYST_FALL",
      "BLOCK_SCULK_CATALYST_HIT",
      "BLOCK_SCULK_CATALYST_PLACE",
      "BLOCK_SCULK_CATALYST_STEP",
      "BLOCK_SCULK_CHARGE",
      "BLOCK_SCULK_FALL",
      "BLOCK_SCULK_HIT",
      "BLOCK_SCULK_PLACE",
      "BLOCK_SCULK_SHRIEKER_BREAK",
      "BLOCK_SCULK_SHRIEKER_FALL",
      "BLOCK_SCULK_SHRIEKER_HIT",
      "BLOCK_SCULK_SHRIEKER_PLACE",
      "BLOCK_SCULK_SHRIEKER_SHRIEK",
      "BLOCK_SCULK_SHRIEKER_STEP",
      "BLOCK_SCULK_SPREAD",
      "BLOCK_SCULK_STEP",
      "BLOCK_SCULK_VEIN_BREAK",
      "BLOCK_SCULK_VEIN_FALL",
      "BLOCK_SCULK_VEIN_HIT",
      "BLOCK_SCULK_VEIN_PLACE",
      "BLOCK_SCULK_VEIN_STEP",
      "ENTITY_ALLAY_AMBIENT_WITHOUT_ITEM",
      "ENTITY_ALLAY_AMBIENT_WITH_ITEM",
      "ENTITY_ALLAY_DEATH",
      "ENTITY_ALLAY_HURT",
      "ENTITY_ALLAY_ITEM_GIVEN",
      "ENTITY_ALLAY_ITEM_TAKEN",
      "ENTITY_ALLAY_ITEM_THROWN",
      "ENTITY_FROG_AMBIENT",
      "ENTITY_FROG_DEATH",
      "ENTITY_FROG_EAT",
      "ENTITY_FROG_HURT",
      "ENTITY_FROG_LAY_SPAWN",
      "ENTITY_FROG_LONG_JUMP",
      "ENTITY_FROG_STEP",
      "ENTITY_FROG_TONGUE",
      "ENTITY_GOAT_HORN_BREAK",
      "ENTITY_GOAT_SCREAMING_HORN_BREAK",
      "ENTITY_PARROT_IMITATE_WARDEN",
      "ENTITY_TADPOLE_DEATH",
      "ENTITY_TADPOLE_FLOP",
      "ENTITY_TADPOLE_GROW_UP",
      "ENTITY_TADPOLE_HURT",
      "ENTITY_WARDEN_AGITATED",
      "ENTITY_WARDEN_AMBIENT",
      "ENTITY_WARDEN_ANGRY",
      "ENTITY_WARDEN_ATTACK_IMPACT",
      "ENTITY_WARDEN_DEATH",
      "ENTITY_WARDEN_DIG",
      "ENTITY_WARDEN_EMERGE",
      "ENTITY_WARDEN_HEARTBEAT",
      "ENTITY_WARDEN_HURT",
      "ENTITY_WARDEN_LISTENING",
      "ENTITY_WARDEN_LISTENING_ANGRY",
      "ENTITY_WARDEN_NEARBY_CLOSE",
      "ENTITY_WARDEN_NEARBY_CLOSER",
      "ENTITY_WARDEN_NEARBY_CLOSEST",
      "ENTITY_WARDEN_ROAR",
      "ENTITY_WARDEN_SNIFF",
      "ENTITY_WARDEN_SONIC_BOOM",
      "ENTITY_WARDEN_SONIC_CHARGE",
      "ENTITY_WARDEN_STEP",
      "ENTITY_WARDEN_TENDRIL_CLICKS",
      "ITEM_BUCKET_EMPTY_TADPOLE",
      "ITEM_BUCKET_FILL_TADPOLE",
      "ITEM_GOAT_HORN_PLAY",
      "ITEM_GOAT_HORN_SOUND_0",
      "ITEM_GOAT_HORN_SOUND_1",
      "ITEM_GOAT_HORN_SOUND_2",
      "ITEM_GOAT_HORN_SOUND_3",
      "ITEM_GOAT_HORN_SOUND_4",
      "ITEM_GOAT_HORN_SOUND_5",
      "ITEM_GOAT_HORN_SOUND_6",
      "ITEM_GOAT_HORN_SOUND_7",
      "MUSIC_OVERWORLD_DEEP_DARK",
      "MUSIC_OVERWORLD_JUNGLE_AND_FOREST",
      "MUSIC_OVERWORLD_OLD_GROWTH_TAIGA",
      "MUSIC_OVERWORLD_SWAMP"
    ],
    "org.bukkit.entity.EntityType": [
      "ALLAY",
      "CHEST_BOAT",
      "FROG",
      "TADPOLE"
    ],
    "org.bukkit.event.entity.EntityPotionEffectEvent.Cause": [
      "WARDEN"
    ],
    "org.bukkit.entity.ZombieVillager": [
      "setConversionTime(int,boolean)"
    ],
    "io.papermc.paper.entity.RelativeTeleportFlag": [
      "PITCH",
      "RelativeTeleportFlag()",
      "YAW"
    ],
    "org.bukkit.map.MapPalette.MapColorCache": [
      "isCached()"
    ],
    "org.bukkit.generator.structure.Structure": [
      "MONUMENT",
      "Structure()",
      "getStructure(String)"
    ],
    "org.bukkit.entity.Wolf": [
      "getTailAngle()",
      "isWet()"
    ],
    "org.bukkit.Vibration": [
      "Vibration(Destination,int)"
    ],
    "org.bukkit.entity.Boat.Type": [
      "MANGROVE",
      "OAK",
      "SPRUCE",
      "Type(Material)",
      "materialBlock"
    ],
    "org.bukkit.entity.Frog.Variant": [
      "COLD",
      "TEMPERATE",
      "WARM"
    ],
    "org.bukkit.potion.PotionEffectType": [
      "DARKNESS"
    ],
    "org.bukkit.Registry": [
      "FROG_VARIANT",
      "STRUCTURE"
    ],
    "org.bukkit.GameRule": [
      "DO_WARDEN_SPAWNING"
    ],
    "org.bukkit.entity.Parrot": [
      "isDancing()"
    ],
    "io.papermc.paper.event.entity.WardenAngerChangeEvent": [
      "WardenAngerChangeEvent(Warden,Entity,int,int)",
      "getOldAnger()",
      "oldAnger"
    ],
    "org.bukkit.entity.Panda": [
      "isScared()",
      "setOnBack(boolean)"
    ],
    "org.bukkit.Tag": [
      "ANCIENT_CITY_REPLACEABLE",
      "COMPLETES_FIND_TREE_TUTORIAL",
      "CONVERTABLE_TO_MUD",
      "DAMPENS_VIBRATIONS",
      "DEAD_BUSH_MAY_PLACE_ON",
      "DRAGON_TRANSPARENT",
      "ENTITY_TYPES_FROG_FOOD",
      "FROGS_SPAWNABLE_ON",
      "FROG_PREFER_JUMP_TO",
      "ITEMS_CHEST_BOATS",
      "ITEMS_COMPASSES",
      "MANGROVE_LOGS",
      "MANGROVE_LOGS_CAN_GROW_THROUGH",
      "MANGROVE_ROOTS_CAN_GROW_THROUGH",
      "NETHER_CARVER_REPLACEABLES",
      "OVERWORLD_CARVER_REPLACEABLES",
      "OVERWORLD_NATURAL_LOGS",
      "POLAR_BEARS_SPAWNABLE_ON_ALTERNATE",
      "SCULK_REPLACEABLE",
      "SCULK_REPLACEABLE_WORLD_GEN",
      "SNAPS_GOAT_HORN",
      "SNOW_LAYER_CANNOT_SURVIVE_ON",
      "SNOW_LAYER_CAN_SURVIVE_ON",
      "WOOL_CARPETS"
    ],
    "org.bukkit.conversations.BooleanPrompt": [
      "FALSE_INPUTS",
      "TRUE_INPUTS",
      "VALID_INPUTS"
    ],
    "org.bukkit.util.StructureSearchResult": [
      "getStructure()"
    ],
    "org.bukkit.block.BlockSupport": [
      "BlockSupport()",
      "RIGID"
    ],
    "com.destroystokyo.paper.event.server.PaperServerListPingEvent": [
      "PaperServerListPingEvent(StatusClient,Component,boolean,int,int,String,int,CachedServerIcon)",
      "PaperServerListPingEvent(StatusClient,String,boolean,int,int,String,int,CachedServerIcon)"
    ],
    "org.bukkit.event.server.ServerListPingEvent": [
      "shouldSendChatPreviews()",
      "ServerListPingEvent(InetAddress,Component,boolean,int)",
      "ServerListPingEvent(InetAddress,Component,boolean,int,int)",
      "ServerListPingEvent(InetAddress,String,boolean,int)",
      "ServerListPingEvent(InetAddress,String,boolean,int,int)",
      "shouldSendChatPreviews"
    ],
    "org.bukkit.Server": [
      "\u003cT\u003egetRegistry(Class)",
      "getMaxChainedNeighborUpdates()",
      "isEnforcingSecureProfiles()"
    ],
    "org.bukkit.GameEvent": [
      "BLOCK_ACTIVATE",
      "BLOCK_DEACTIVATE",
      "DRINK",
      "ELYTRA_GLIDE",
      "ENTITY_DAMAGE",
      "ENTITY_DIE",
      "ENTITY_DYING",
      "ENTITY_INTERACT",
      "ENTITY_ROAR",
      "ENTITY_SHAKE",
      "INSTRUMENT_PLAY",
      "ITEM_INTERACT_FINISH",
      "ITEM_INTERACT_START",
      "NOTE_BLOCK_PLAY",
      "SCULK_SENSOR_TENDRILS_CLICKING"
    ],
    "org.bukkit.block.data.type.SculkCatalyst": [
      "isBloom()",
      "setBloom(boolean)"
    ],
    "org.bukkit.entity.HumanEntity": [
      "getLastDeathLocation()",
      "getFishHook()",
      "setLastDeathLocation(Location)"
    ],
    "org.bukkit.event.world.GenericGameEvent": [
      "GenericGameEvent(GameEvent,Location,Entity,int,boolean)"
    ],
    "org.bukkit.entity.Warden": [
      "getAnger(Entity)",
      "increaseAnger(Entity,int)",
      "setAnger(Entity,int)"
    ],
    "org.bukkit.entity.Boat.Status": [
      "IN_AIR",
      "IN_WATER",
      "ON_LAND",
      "UNDER_FLOWING_WATER",
      "UNDER_WATER"
    ],
    "org.bukkit.entity.memory.MemoryKey": [
      "ITEM_PICKUP_COOLDOWN_TICKS",
      "LIKED_NOTEBLOCK_COOLDOWN_TICKS",
      "LIKED_NOTEBLOCK_POSITION",
      "LIKED_PLAYER"
    ],
    "org.bukkit.event.world.WorldEvent": [
      "WorldEvent(World,boolean)"
    ],
    "org.bukkit.Particle": [
      "SHRIEK",
      "SCULK_CHARGE",
      "SCULK_CHARGE_POP",
      "SCULK_SOUL"
    ],
    "org.bukkit.event.player.PlayerTeleportEvent": [
      "PlayerTeleportEvent(Player,Location,Location,TeleportCause,boolean,Set)",
      "getRelativeTeleportationFlags()",
      "teleportFlagSet",
      "willDismountPlayer()"
    ],
    "org.bukkit.entity.Frog": [
      "getTongueTarget()",
      "setTongueTarget(Entity)"
    ],
    "org.bukkit.entity.Pose": [
      "CROAKING",
      "DIGGING",
      "EMERGING",
      "ROARING",
      "SNIFFING",
      "USING_TONGUE"
    ],
    "org.bukkit.generator.structure.StructureType": [
      "StructureType()",
      "getStructureType(String)"
    ],
    "org.bukkit.map.MapPalette": [
      "mapColorCache",
      "setMapColorCache(MapColorCache)"
    ],
    "org.bukkit.entity.Goat": [
      "hasLeftHorn()",
      "hasRightHorn()",
      "setLeftHorn(boolean)",
      "setRightHorn(boolean)"
    ]
  },
  "membersRemoved": {
    "org.bukkit.event.world.GenericGameEvent": [
      "GenericGameEvent(GameEvent,Location,Entity,int)"
    ],
    "org.bukkit.event.server.ServerListPingEvent": [
      "ServerListPingEvent(InetAddress,Component,int)",
      "ServerListPingEvent(InetAddress,Component,int,int)",
      "ServerListPingEvent(InetAddress,String,int)",
      "ServerListPingEvent(InetAddress,String,int,int)"
    ],
    "org.bukkit.GameEvent": [
      "FISHING_ROD_CAST",
      "FISHING_ROD_REEL_IN",
      "MINECART_MOVING"
    ],
    "com.destroystokyo.paper.event.server.PaperServerListPingEvent": [
      "PaperServerListPingEvent(StatusClient,Component,int,int,String,int,CachedServerIcon)",
      "PaperServerListPingEvent(StatusClient,String,int,int,String,int,CachedServerIcon)"
    ]
  },
  "membersChanged": {
    "org.bukkit.event.world.GenericGameEvent": [
      "GenericGameEvent(GameEvent,Location,Entity,int)"
    ],
    "org.bukkit.event.server.ServerListPingEvent": [
      "ServerListPingEvent(InetAddress,Component,int)",
      "ServerListPingEvent(InetAddress,Component,int,int)",
      "ServerListPingEvent(InetAddress,String,int)",
      "ServerListPingEvent(InetAddress,String,int,int)"
    ],
    "org.bukkit.GameEvent": [
      "FISHING_ROD_CAST",
      "FISHING_ROD_REEL_IN",
      "MINECART_MOVING"
    ],
    "com.destroystokyo.paper.event.server.PaperServerListPingEvent": [
      "PaperServerListPingEvent(StatusClient,Component,int,int,String,int,CachedServerIcon)",
      "PaperServerListPingEvent(StatusClient,String,int,int,String,int,CachedServerIcon)"
    ]
  }
}