{
  "versionA": "1.15.2",
  "versionB": "1.16.1",
  "packagesAdded": [],
  "packagesRemoved": [],
  "packagesChanged": [
    "com.destroystokyo.paper",
    "com.destroystokyo.paper.block",
    "com.destroystokyo.paper.entity",
    "com.destroystokyo.paper.entity.ai",
    "com.destroystokyo.paper.entity.villager",
    "com.destroystokyo.paper.event.block",
    "com.destroystokyo.paper.event.entity",
    "com.destroystokyo.paper.event.executor",
    "com.destroystokyo.paper.event.executor.asm",
    "com.destroystokyo.paper.event.inventory",
    "com.destroystokyo.paper.event.player",
    "com.destroystokyo.paper.event.profile",
    "com.destroystokyo.paper.event.server",
    "com.destroystokyo.paper.exception",
    "com.destroystokyo.paper.inventory",
    "com.destroystokyo.paper.inventory.meta",
    "com.destroystokyo.paper.loottable",
    "com.destroystokyo.paper.network",
    "com.destroystokyo.paper.profile",
    "com.destroystokyo.paper.util",
    "com.destroystokyo.paper.utils",
    "org.bukkit",
    "org.bukkit.advancement",
    "org.bukkit.attribute",
    "org.bukkit.block",
    "org.bukkit.block.banner",
    "org.bukkit.block.data",
    "org.bukkit.block.data.type",
    "org.bukkit.block.structure",
    "org.bukkit.boss",
    "org.bukkit.command",
    "org.bukkit.command.defaults",
    "org.bukkit.configuration",
    "org.bukkit.configuration.file",
    "org.bukkit.configuration.serialization",
    "org.bukkit.conversations",
    "org.bukkit.enchantments",
    "org.bukkit.entity",
    "org.bukkit.entity.memory",
    "org.bukkit.entity.minecart",
    "org.bukkit.event",
    "org.bukkit.event.block",
    "org.bukkit.event.command",
    "org.bukkit.event.enchantment",
    "org.bukkit.event.entity",
    "org.bukkit.event.hanging",
    "org.bukkit.event.inventory",
    "org.bukkit.event.player",
    "org.bukkit.event.raid",
    "org.bukkit.event.server",
    "org.bukkit.event.vehicle",
    "org.bukkit.event.weather",
    "org.bukkit.event.world",
    "org.bukkit.generator",
    "org.bukkit.help",
    "org.bukkit.inventory",
    "org.bukkit.inventory.meta",
    "org.bukkit.inventory.meta.tags",
    "org.bukkit.loot",
    "org.bukkit.map",
    "org.bukkit.material",
    "org.bukkit.material.types",
    "org.bukkit.metadata",
    "org.bukkit.permissions",
    "org.bukkit.persistence",
    "org.bukkit.plugin",
    "org.bukkit.plugin.java",
    "org.bukkit.plugin.messaging",
    "org.bukkit.potion",
    "org.bukkit.projectiles",
    "org.bukkit.scheduler",
    "org.bukkit.scoreboard",
    "org.bukkit.util",
    "org.bukkit.util.io",
    "org.bukkit.util.noise",
    "org.bukkit.util.permissions",
    "org.spigotmc",
    "org.spigotmc.event.entity",
    "org.spigotmc.event.player"
  ],
  "classesAdded": [
    "com.destroystokyo.paper.event.inventory.PrepareResultEvent",
    "org.bukkit.block.Lidded",
    "org.bukkit.block.data.type.Jigsaw",
    "org.bukkit.block.data.type.Jigsaw.Orientation",
    "org.bukkit.block.data.type.RespawnAnchor",
    "org.bukkit.block.data.type.Wall",
    "org.bukkit.block.data.type.Wall.Height",
    "org.bukkit.entity.Hoglin",
    "org.bukkit.entity.Piglin",
    "org.bukkit.entity.Steerable",
    "org.bukkit.entity.Strider",
    "org.bukkit.entity.Zoglin",
    "org.bukkit.event.entity.EntityEnterLoveModeEvent",
    "org.bukkit.event.entity.StriderTemperatureChangeEvent",
    "org.bukkit.event.inventory.PrepareSmithingEvent",
    "org.bukkit.event.player.PlayerHarvestBlockEvent",
    "org.bukkit.inventory.SmithingInventory",
    "org.bukkit.inventory.SmithingRecipe",
    "org.bukkit.inventory.meta.CompassMeta"
  ],
  "classesRemoved": [],
  "classesChanged": [
    "com.destroystokyo.paper.MaterialTags",
    "com.destroystokyo.paper.entity.ai.VanillaGoal",
    "com.destroystokyo.paper.event.inventory.PrepareGrindstoneEvent",
    "org.bukkit.Bukkit",
    "org.bukkit.ChatColor",
    "org.bukkit.EntityEffect",
    "org.bukkit.GameRule",
    "org.bukkit.Material",
    "org.bukkit.Particle",
    "org.bukkit.Registry",
    "org.bukkit.Server",
    "org.bukkit.Sound",
    "org.bukkit.Statistic",
    "org.bukkit.StructureType",
    "org.bukkit.Tag",
    "org.bukkit.TreeType",
    "org.bukkit.World",
    "org.bukkit.WorldType",
    "org.bukkit.attribute.Attribute",
    "org.bukkit.block.Biome",
    "org.bukkit.block.Jukebox",
    "org.bukkit.block.banner.PatternType",
    "org.bukkit.boss.DragonBattle",
    "org.bukkit.command.defaults.PluginsCommand",
    "org.bukkit.command.defaults.VersionCommand",
    "org.bukkit.configuration.file.YamlConfiguration",
    "org.bukkit.enchantments.Enchantment",
    "org.bukkit.enchantments.EnchantmentTarget",
    "org.bukkit.entity.Entity",
    "org.bukkit.entity.EntityType",
    "org.bukkit.entity.HumanEntity",
    "org.bukkit.entity.ItemFrame",
    "org.bukkit.entity.LivingEntity",
    "org.bukkit.entity.Pig",
    "org.bukkit.entity.Player",
    "org.bukkit.entity.memory.MemoryKey",
    "org.bukkit.event.entity.EntityTargetEvent.TargetReason",
    "org.bukkit.event.inventory.ClickType",
    "org.bukkit.event.inventory.InventoryType",
    "org.bukkit.event.inventory.PrepareAnvilEvent",
    "org.bukkit.event.player.PlayerRespawnEvent",
    "org.bukkit.generator.ChunkGenerator",
    "org.bukkit.inventory.meta.ItemMeta",
    "org.bukkit.loot.LootTables",
    "org.bukkit.persistence.PersistentDataContainer",
    "org.bukkit.persistence.PersistentDataType",
    "org.bukkit.plugin.PluginDescriptionFile",
    "org.bukkit.util.Vector"
  ],
  "membersAdded": {
    "org.bukkit.TreeType": [
      "CRIMSON_FUNGUS",
      "WARPED_FUNGUS"
    ],
    "org.bukkit.event.entity.EntityTargetEvent.TargetReason": [
      "TARGET_INVALID",
      "TARGET_OTHER_LEVEL"
    ],
    "org.bukkit.block.data.type.RespawnAnchor": [
      "getCharges()",
      "getMaximumCharges()",
      "setCharges(int)"
    ],
    "org.bukkit.EntityEffect": [
      "BREAK_EQUIPMENT_BOOTS",
      "BREAK_EQUIPMENT_CHESTPLATE",
      "BREAK_EQUIPMENT_HELMET",
      "BREAK_EQUIPMENT_LEGGINGS",
      "BREAK_EQUIPMENT_MAIN_HAND",
      "BREAK_EQUIPMENT_OFF_HAND",
      "CAT_TAME_FAIL",
      "CAT_TAME_SUCCESS",
      "DOLPHIN_FED",
      "FOX_CHEW",
      "HURT_BERRY_BUSH",
      "PLAYER_BAD_OMEN_RAID",
      "RAVAGER_STUNNED",
      "TELEPORT_ENDER",
      "VILLAGER_SPLASH"
    ],
    "org.bukkit.boss.DragonBattle": [
      "generateEndPortal(boolean)"
    ],
    "org.bukkit.enchantments.Enchantment": [
      "SOUL_SPEED"
    ],
    "org.bukkit.inventory.SmithingRecipe": [
      "SmithingRecipe(NamespacedKey,ItemStack,RecipeChoice,RecipeChoice)",
      "addition",
      "base",
      "getAddition()",
      "getBase()"
    ],
    "org.bukkit.Statistic": [
      "INTERACT_WITH_SMITHING_TABLE",
      "STRIDER_ONE_CM",
      "TARGET_HIT"
    ],
    "org.bukkit.block.Jukebox": [
      "stopPlaying()"
    ],
    "org.bukkit.entity.Player": [
      "getClientBrandName()",
      "sendActionBar(BaseComponent...)"
    ],
    "org.bukkit.entity.Piglin": [
      "isImmuneToZombification()",
      "setImmuneToZombification(boolean)",
      "isAbleToHunt()",
      "setIsAbleToHunt(boolean)"
    ],
    "org.bukkit.block.Biome": [
      "BASALT_DELTAS",
      "CRIMSON_FOREST",
      "NETHER_WASTES",
      "SOUL_SAND_VALLEY",
      "WARPED_FOREST"
    ],
    "org.bukkit.generator.ChunkGenerator": [
      "createVanillaChunkData(World,int,int)"
    ],
    "org.bukkit.enchantments.EnchantmentTarget": [
      "VANISHABLE"
    ],
    "com.destroystokyo.paper.entity.ai.VanillaGoal": [
      "STROLL_VILLAGE_GOLEM",
      "UNIVERSAL_ANGER_RESET"
    ],
    "org.bukkit.event.inventory.PrepareSmithingEvent": [
      "PrepareSmithingEvent(InventoryView,ItemStack)"
    ],
    "org.bukkit.block.data.type.Jigsaw": [
      "getOrientation()",
      "setOrientation(Orientation)"
    ],
    "org.bukkit.entity.ItemFrame": [
      "isFixed()",
      "setFixed(boolean)"
    ],
    "org.bukkit.World": [
      "getTicksPerWaterAmbientSpawns()",
      "getWaterAmbientSpawnLimit()",
      "setTicksPerWaterAmbientSpawns(int)",
      "setWaterAmbientSpawnLimit(int)"
    ],
    "org.bukkit.event.entity.EntityEnterLoveModeEvent": [
      "EntityEnterLoveModeEvent(Animals,HumanEntity,int)",
      "getHumanEntity()",
      "getTicksInLove()",
      "humanEntity",
      "setTicksInLove(int)",
      "ticksInLove"
    ],
    "com.destroystokyo.paper.event.inventory.PrepareResultEvent": [
      "PrepareResultEvent(InventoryView,ItemStack)"
    ],
    "org.bukkit.Material": [
      "SOUL_TORCH",
      "ANCIENT_DEBRIS",
      "BASALT",
      "BLACKSTONE",
      "BLACKSTONE_SLAB",
      "BLACKSTONE_STAIRS",
      "BLACKSTONE_WALL",
      "CHAIN",
      "CHISELED_NETHER_BRICKS",
      "CHISELED_POLISHED_BLACKSTONE",
      "CRACKED_NETHER_BRICKS",
      "CRACKED_POLISHED_BLACKSTONE_BRICKS",
      "CRIMSON_BUTTON",
      "CRIMSON_DOOR",
      "CRIMSON_FENCE",
      "CRIMSON_FENCE_GATE",
      "CRIMSON_HYPHAE",
      "CRIMSON_NYLIUM",
      "CRIMSON_PLANKS",
      "CRIMSON_PRESSURE_PLATE",
      "CRIMSON_ROOTS",
      "CRIMSON_SIGN",
      "CRIMSON_SLAB",
      "CRIMSON_STAIRS",
      "CRIMSON_STEM",
      "CRIMSON_TRAPDOOR",
      "CRIMSON_WALL_SIGN",
      "CRYING_OBSIDIAN",
      "GILDED_BLACKSTONE",
      "HOGLIN_SPAWN_EGG",
      "LODESTONE",
      "NETHERITE_AXE",
      "NETHERITE_BLOCK",
      "NETHERITE_BOOTS",
      "NETHERITE_CHESTPLATE",
      "NETHERITE_HELMET",
      "NETHERITE_HOE",
      "NETHERITE_INGOT",
      "NETHERITE_LEGGINGS",
      "NETHERITE_PICKAXE",
      "NETHERITE_SCRAP",
      "NETHERITE_SHOVEL",
      "NETHERITE_SWORD",
      "NETHER_GOLD_ORE",
      "NETHER_SPROUTS",
      "PIGLIN_BANNER_PATTERN",
      "PIGLIN_SPAWN_EGG",
      "POLISHED_BASALT",
      "POLISHED_BLACKSTONE",
      "POLISHED_BLACKSTONE_BRICKS",
      "POLISHED_BLACKSTONE_BRICK_SLAB",
      "POLISHED_BLACKSTONE_BRICK_STAIRS",
      "POLISHED_BLACKSTONE_BRICK_WALL",
      "POLISHED_BLACKSTONE_BUTTON",
      "POLISHED_BLACKSTONE_PRESSURE_PLATE",
      "POLISHED_BLACKSTONE_SLAB",
      "POLISHED_BLACKSTONE_STAIRS",
      "POLISHED_BLACKSTONE_WALL",
      "POTTED_CRIMSON_FUNGUS",
      "POTTED_CRIMSON_ROOTS",
      "POTTED_WARPED_FUNGUS",
      "POTTED_WARPED_ROOTS",
      "QUARTZ_BRICKS",
      "RESPAWN_ANCHOR",
      "SHROOMLIGHT",
      "SOUL_CAMPFIRE",
      "SOUL_FIRE",
      "SOUL_LANTERN",
      "SOUL_SOIL",
      "SOUL_WALL_TORCH",
      "STRIDER_SPAWN_EGG",
      "STRIPPED_CRIMSON_HYPHAE",
      "STRIPPED_CRIMSON_STEM",
      "STRIPPED_WARPED_HYPHAE",
      "STRIPPED_WARPED_STEM",
      "TWISTING_VINES",
      "TWISTING_VINES_PLANT",
      "WARPED_BUTTON",
      "WARPED_DOOR",
      "WARPED_FENCE",
      "WARPED_FENCE_GATE",
      "WARPED_FUNGUS_ON_A_STICK",
      "WARPED_HYPHAE",
      "WARPED_NYLIUM",
      "WARPED_PLANKS",
      "WARPED_PRESSURE_PLATE",
      "WARPED_ROOTS",
      "WARPED_SIGN",
      "WARPED_SLAB",
      "WARPED_STAIRS",
      "WARPED_STEM",
      "WARPED_TRAPDOOR",
      "WARPED_WALL_SIGN",
      "WARPED_WART_BLOCK",
      "WEEPING_VINES",
      "WEEPING_VINES_PLANT",
      "ZOGLIN_SPAWN_EGG",
      "ZOMBIFIED_PIGLIN_SPAWN_EGG"
    ],
    "org.bukkit.persistence.PersistentDataContainer": [
      "getKeys()"
    ],
    "org.bukkit.loot.LootTables": [
      "RUINED_PORTAL",
      "BASTION_BRIDGE",
      "BASTION_HOGLIN_STABLE",
      "BASTION_OTHER",
      "BASTION_TREASURE",
      "PIGLIN_BARTERING"
    ],
    "org.bukkit.entity.Entity": [
      "isInBubbleColumn()",
      "isInLava()",
      "isInRain()",
      "isInWater()",
      "isInWaterOrBubbleColumn()",
      "isInWaterOrRain()",
      "isInWaterOrRainOrBubbleColumn()"
    ],
    "org.bukkit.entity.Hoglin": [
      "isAbleToBeHunted()",
      "setIsAbleToBeHunted(boolean)"
    ],
    "org.bukkit.event.entity.StriderTemperatureChangeEvent": [
      "isShivering()",
      "StriderTemperatureChangeEvent(Strider,boolean)",
      "shivering"
    ],
    "com.destroystokyo.paper.MaterialTags": [
      "AXES",
      "BOOTS",
      "BOWS",
      "CHESTPLATES",
      "CHEST_EQUIPPABLE",
      "HEAD_EQUIPPABLE",
      "HELMETS",
      "HOES",
      "LANTERNS",
      "LEGGINGS",
      "PICKAXES",
      "SHOVELS",
      "SWORDS",
      "THROWABLE_PROJECTILES",
      "TORCHES"
    ],
    "org.bukkit.StructureType": [
      "BASTION_REMNANT",
      "NETHER_FOSSIL"
    ],
    "org.bukkit.command.defaults.PluginsCommand": [
      "getPluginListSpigot()"
    ],
    "org.bukkit.Sound": [
      "MUSIC_DISC_PIGSTEP",
      "AMBIENT_BASALT_DELTAS_ADDITIONS",
      "AMBIENT_BASALT_DELTAS_LOOP",
      "AMBIENT_BASALT_DELTAS_MOOD",
      "AMBIENT_CRIMSON_FOREST_ADDITIONS",
      "AMBIENT_CRIMSON_FOREST_LOOP",
      "AMBIENT_CRIMSON_FOREST_MOOD",
      "AMBIENT_NETHER_WASTES_ADDITIONS",
      "AMBIENT_NETHER_WASTES_LOOP",
      "AMBIENT_NETHER_WASTES_MOOD",
      "AMBIENT_SOUL_SAND_VALLEY_ADDITIONS",
      "AMBIENT_SOUL_SAND_VALLEY_LOOP",
      "AMBIENT_SOUL_SAND_VALLEY_MOOD",
      "AMBIENT_WARPED_FOREST_ADDITIONS",
      "AMBIENT_WARPED_FOREST_LOOP",
      "AMBIENT_WARPED_FOREST_MOOD",
      "BLOCK_ANCIENT_DEBRIS_BREAK",
      "BLOCK_ANCIENT_DEBRIS_FALL",
      "BLOCK_ANCIENT_DEBRIS_HIT",
      "BLOCK_ANCIENT_DEBRIS_PLACE",
      "BLOCK_ANCIENT_DEBRIS_STEP",
      "BLOCK_BASALT_BREAK",
      "BLOCK_BASALT_FALL",
      "BLOCK_BASALT_HIT",
      "BLOCK_BASALT_PLACE",
      "BLOCK_BASALT_STEP",
      "BLOCK_BONE_BLOCK_BREAK",
      "BLOCK_BONE_BLOCK_FALL",
      "BLOCK_BONE_BLOCK_HIT",
      "BLOCK_BONE_BLOCK_PLACE",
      "BLOCK_BONE_BLOCK_STEP",
      "BLOCK_CHAIN_BREAK",
      "BLOCK_CHAIN_FALL",
      "BLOCK_CHAIN_HIT",
      "BLOCK_CHAIN_PLACE",
      "BLOCK_CHAIN_STEP",
      "BLOCK_FUNGUS_BREAK",
      "BLOCK_FUNGUS_FALL",
      "BLOCK_FUNGUS_HIT",
      "BLOCK_FUNGUS_PLACE",
      "BLOCK_FUNGUS_STEP",
      "BLOCK_GILDED_BLACKSTONE_BREAK",
      "BLOCK_GILDED_BLACKSTONE_FALL",
      "BLOCK_GILDED_BLACKSTONE_HIT",
      "BLOCK_GILDED_BLACKSTONE_PLACE",
      "BLOCK_GILDED_BLACKSTONE_STEP",
      "BLOCK_LODESTONE_BREAK",
      "BLOCK_LODESTONE_FALL",
      "BLOCK_LODESTONE_HIT",
      "BLOCK_LODESTONE_PLACE",
      "BLOCK_LODESTONE_STEP",
      "BLOCK_NETHERITE_BLOCK_BREAK",
      "BLOCK_NETHERITE_BLOCK_FALL",
      "BLOCK_NETHERITE_BLOCK_HIT",
      "BLOCK_NETHERITE_BLOCK_PLACE",
      "BLOCK_NETHERITE_BLOCK_STEP",
      "BLOCK_NETHERRACK_BREAK",
      "BLOCK_NETHERRACK_FALL",
      "BLOCK_NETHERRACK_HIT",
      "BLOCK_NETHERRACK_PLACE",
      "BLOCK_NETHERRACK_STEP",
      "BLOCK_NETHER_BRICKS_BREAK",
      "BLOCK_NETHER_BRICKS_FALL",
      "BLOCK_NETHER_BRICKS_HIT",
      "BLOCK_NETHER_BRICKS_PLACE",
      "BLOCK_NETHER_BRICKS_STEP",
      "BLOCK_NETHER_GOLD_ORE_BREAK",
      "BLOCK_NETHER_GOLD_ORE_FALL",
      "BLOCK_NETHER_GOLD_ORE_HIT",
      "BLOCK_NETHER_GOLD_ORE_PLACE",
      "BLOCK_NETHER_GOLD_ORE_STEP",
      "BLOCK_NETHER_ORE_BREAK",
      "BLOCK_NETHER_ORE_FALL",
      "BLOCK_NETHER_ORE_HIT",
      "BLOCK_NETHER_ORE_PLACE",
      "BLOCK_NETHER_ORE_STEP",
      "BLOCK_NETHER_SPROUTS_BREAK",
      "BLOCK_NETHER_SPROUTS_FALL",
      "BLOCK_NETHER_SPROUTS_HIT",
      "BLOCK_NETHER_SPROUTS_PLACE",
      "BLOCK_NETHER_SPROUTS_STEP",
      "BLOCK_NYLIUM_BREAK",
      "BLOCK_NYLIUM_FALL",
      "BLOCK_NYLIUM_HIT",
      "BLOCK_NYLIUM_PLACE",
      "BLOCK_NYLIUM_STEP",
      "BLOCK_RESPAWN_ANCHOR_AMBIENT",
      "BLOCK_RESPAWN_ANCHOR_CHARGE",
      "BLOCK_RESPAWN_ANCHOR_DEPLETE",
      "BLOCK_RESPAWN_ANCHOR_SET_SPAWN",
      "BLOCK_ROOTS_BREAK",
      "BLOCK_ROOTS_FALL",
      "BLOCK_ROOTS_HIT",
      "BLOCK_ROOTS_PLACE",
      "BLOCK_ROOTS_STEP",
      "BLOCK_SHROOMLIGHT_BREAK",
      "BLOCK_SHROOMLIGHT_FALL",
      "BLOCK_SHROOMLIGHT_HIT",
      "BLOCK_SHROOMLIGHT_PLACE",
      "BLOCK_SHROOMLIGHT_STEP",
      "BLOCK_SMITHING_TABLE_USE",
      "BLOCK_SOUL_SAND_BREAK",
      "BLOCK_SOUL_SAND_FALL",
      "BLOCK_SOUL_SAND_HIT",
      "BLOCK_SOUL_SAND_PLACE",
      "BLOCK_SOUL_SAND_STEP",
      "BLOCK_SOUL_SOIL_BREAK",
      "BLOCK_SOUL_SOIL_FALL",
      "BLOCK_SOUL_SOIL_HIT",
      "BLOCK_SOUL_SOIL_PLACE",
      "BLOCK_SOUL_SOIL_STEP",
      "BLOCK_STEM_BREAK",
      "BLOCK_STEM_FALL",
      "BLOCK_STEM_HIT",
      "BLOCK_STEM_PLACE",
      "BLOCK_STEM_STEP",
      "BLOCK_VINE_STEP",
      "BLOCK_WART_BLOCK_BREAK",
      "BLOCK_WART_BLOCK_FALL",
      "BLOCK_WART_BLOCK_HIT",
      "BLOCK_WART_BLOCK_PLACE",
      "BLOCK_WART_BLOCK_STEP",
      "BLOCK_WEEPING_VINES_BREAK",
      "BLOCK_WEEPING_VINES_FALL",
      "BLOCK_WEEPING_VINES_HIT",
      "BLOCK_WEEPING_VINES_PLACE",
      "BLOCK_WEEPING_VINES_STEP",
      "ENTITY_DONKEY_EAT",
      "ENTITY_FOX_TELEPORT",
      "ENTITY_HOGLIN_AMBIENT",
      "ENTITY_HOGLIN_ANGRY",
      "ENTITY_HOGLIN_ATTACK",
      "ENTITY_HOGLIN_CONVERTED_TO_ZOMBIFIED",
      "ENTITY_HOGLIN_DEATH",
      "ENTITY_HOGLIN_HURT",
      "ENTITY_HOGLIN_RETREAT",
      "ENTITY_HOGLIN_STEP",
      "ENTITY_MULE_ANGRY",
      "ENTITY_MULE_EAT",
      "ENTITY_PARROT_IMITATE_HOGLIN",
      "ENTITY_PARROT_IMITATE_PIGLIN",
      "ENTITY_PARROT_IMITATE_ZOGLIN",
      "ENTITY_PIGLIN_ADMIRING_ITEM",
      "ENTITY_PIGLIN_AMBIENT",
      "ENTITY_PIGLIN_ANGRY",
      "ENTITY_PIGLIN_CELEBRATE",
      "ENTITY_PIGLIN_CONVERTED_TO_ZOMBIFIED",
      "ENTITY_PIGLIN_DEATH",
      "ENTITY_PIGLIN_HURT",
      "ENTITY_PIGLIN_JEALOUS",
      "ENTITY_PIGLIN_RETREAT",
      "ENTITY_PIGLIN_STEP",
      "ENTITY_SNOW_GOLEM_SHEAR",
      "ENTITY_STRIDER_AMBIENT",
      "ENTITY_STRIDER_DEATH",
      "ENTITY_STRIDER_EAT",
      "ENTITY_STRIDER_HAPPY",
      "ENTITY_STRIDER_HURT",
      "ENTITY_STRIDER_RETREAT",
      "ENTITY_STRIDER_SADDLE",
      "ENTITY_STRIDER_STEP",
      "ENTITY_STRIDER_STEP_LAVA",
      "ENTITY_ZOGLIN_AMBIENT",
      "ENTITY_ZOGLIN_ANGRY",
      "ENTITY_ZOGLIN_ATTACK",
      "ENTITY_ZOGLIN_DEATH",
      "ENTITY_ZOGLIN_HURT",
      "ENTITY_ZOGLIN_STEP",
      "ENTITY_ZOMBIFIED_PIGLIN_AMBIENT",
      "ENTITY_ZOMBIFIED_PIGLIN_ANGRY",
      "ENTITY_ZOMBIFIED_PIGLIN_DEATH",
      "ENTITY_ZOMBIFIED_PIGLIN_HURT",
      "ITEM_ARMOR_EQUIP_NETHERITE",
      "ITEM_LODESTONE_COMPASS_LOCK",
      "MUSIC_NETHER_BASALT_DELTAS",
      "MUSIC_NETHER_CRIMSON_FOREST",
      "MUSIC_NETHER_NETHER_WASTES",
      "MUSIC_NETHER_SOUL_SAND_VALLEY",
      "MUSIC_NETHER_WARPED_FOREST",
      "PARTICLE_SOUL_ESCAPE"
    ],
    "org.bukkit.entity.LivingEntity": [
      "getCollidableExemptions()"
    ],
    "org.bukkit.entity.EntityType": [
      "PIGLIN",
      "HOGLIN",
      "STRIDER",
      "ZOGLIN",
      "ZOMBIFIED_PIGLIN"
    ],
    "org.bukkit.command.defaults.VersionCommand": [
      "getNameList(List)"
    ],
    "org.bukkit.persistence.PersistentDataType": [
      "TAG_CONTAINER_ARRAY"
    ],
    "org.bukkit.Registry": [
      "ATTRIBUTE"
    ],
    "org.bukkit.GameRule": [
      "FORGIVE_DEAD_PLAYERS"
    ],
    "org.bukkit.event.inventory.ClickType": [
      "SWAP_OFFHAND"
    ],
    "org.bukkit.block.Lidded": [
      "open()"
    ],
    "org.bukkit.Tag": [
      "BEACON_BASE_BLOCKS",
      "CAMPFIRES",
      "CLIMBABLE",
      "CRIMSON_STEMS",
      "GOLD_ORES",
      "GUARDED_BY_PIGLINS",
      "HOGLIN_REPELLENTS",
      "INFINIBURN_END",
      "INFINIBURN_NETHER",
      "INFINIBURN_OVERWORLD",
      "ITEMS_BEACON_PAYMENT_ITEMS",
      "ITEMS_CREEPER_DROP_MUSIC_DISCS",
      "ITEMS_FURNACE_MATERIALS",
      "ITEMS_PIGLIN_LOVED",
      "ITEMS_STONE_TOOL_MATERIALS",
      "LOGS_THAT_BURN",
      "NON_FLAMMABLE_WOOD",
      "NYLIUM",
      "PIGLIN_REPELLENTS",
      "PREVENT_MOB_SPAWNING_INSIDE",
      "SOUL_FIRE_BASE_BLOCKS",
      "SOUL_SPEED_BLOCKS",
      "STONE_PRESSURE_PLATES",
      "STRIDER_WARM_BLOCKS",
      "UNSTABLE_BOTTOM_CENTER",
      "WALL_POST_OVERRIDE",
      "WARPED_STEMS",
      "WART_BLOCKS",
      "WITHER_SUMMON_BASE_BLOCKS"
    ],
    "org.bukkit.block.data.type.Wall.Height": [
      "Height()"
    ],
    "org.bukkit.inventory.meta.ItemMeta": [
      "getDisplayNameComponent()",
      "getLoreComponents()",
      "setDisplayNameComponent(BaseComponent...)",
      "setLoreComponents(List)"
    ],
    "org.bukkit.event.player.PlayerHarvestBlockEvent": [
      "PlayerHarvestBlockEvent(Player,Block,List)",
      "getHarvestedBlock()",
      "getItemsHarvested()",
      "harvestedBlock",
      "itemsHarvested"
    ],
    "org.bukkit.block.data.type.Wall": [
      "getHeight(BlockFace)",
      "isUp()",
      "setHeight(BlockFace,Height)",
      "setUp(boolean)"
    ],
    "org.bukkit.event.player.PlayerRespawnEvent": [
      "PlayerRespawnEvent(Player,Location,boolean,boolean)",
      "isAnchorSpawn",
      "isAnchorSpawn()"
    ],
    "org.bukkit.entity.Steerable": [
      "getBoostTicks()",
      "getCurrentBoostTicks()",
      "getSteerMaterial()",
      "setBoostTicks(int)",
      "setCurrentBoostTicks(int)"
    ],
    "org.bukkit.entity.Strider": [
      "setShivering(boolean)"
    ],
    "org.bukkit.Server": [
      "getRecipe(NamespacedKey)"
    ],
    "org.bukkit.entity.HumanEntity": [
      "getDiscoveredRecipes()",
      "hasDiscoveredRecipe(NamespacedKey)"
    ],
    "org.bukkit.attribute.Attribute": [
      "Attribute(String)",
      "GENERIC_ATTACK_KNOCKBACK"
    ],
    "org.bukkit.event.inventory.InventoryType": [
      "SMITHING"
    ],
    "org.bukkit.entity.memory.MemoryKey": [
      "UNIVERSAL_ANGER",
      "ADMIRING_DISABLED",
      "ADMIRING_ITEM",
      "ANGRY_AT",
      "HUNTED_RECENTLY",
      "POTENTIAL_JOB_SITE"
    ],
    "org.bukkit.util.Vector": [
      "normalizeZeros()"
    ],
    "org.bukkit.Particle": [
      "ASH",
      "CRIMSON_SPORE",
      "DRIPPING_OBSIDIAN_TEAR",
      "FALLING_OBSIDIAN_TEAR",
      "LANDING_OBSIDIAN_TEAR",
      "REVERSE_PORTAL",
      "SOUL",
      "SOUL_FIRE_FLAME",
      "WARPED_SPORE",
      "WHITE_ASH"
    ],
    "org.bukkit.block.data.type.Jigsaw.Orientation": [
      "DOWN_EAST",
      "DOWN_NORTH",
      "DOWN_SOUTH",
      "DOWN_WEST",
      "EAST_UP",
      "NORTH_UP",
      "Orientation()",
      "SOUTH_UP",
      "UP_EAST",
      "UP_NORTH",
      "UP_SOUTH",
      "UP_WEST",
      "WEST_UP"
    ],
    "org.bukkit.configuration.file.YamlConfiguration": [
      "loaderOptions"
    ],
    "org.bukkit.inventory.meta.CompassMeta": [
      "getLodestone()",
      "hasLodestone()",
      "isLodestoneTracked()",
      "setLodestone(Location)",
      "setLodestoneTracked(boolean)"
    ],
    "org.bukkit.ChatColor": [
      "HEX_COLOR_PATTERN"
    ],
    "org.bukkit.plugin.PluginDescriptionFile": [
      "contributors",
      "getContributors()"
    ]
  },
  "membersRemoved": {
    "org.bukkit.attribute.Attribute": [
      "Attribute()"
    ],
    "org.bukkit.Sound": [
      "ENTITY_ZOMBIE_PIGMAN_AMBIENT",
      "ENTITY_ZOMBIE_PIGMAN_ANGRY",
      "ENTITY_ZOMBIE_PIGMAN_DEATH",
      "ENTITY_ZOMBIE_PIGMAN_HURT",
      "MUSIC_NETHER"
    ],
    "org.bukkit.entity.EntityType": [
      "PIG_ZOMBIE"
    ],
    "org.bukkit.WorldType": [
      "BUFFET",
      "CUSTOMIZED",
      "VERSION_1_1"
    ],
    "org.bukkit.Material": [
      "ZOMBIE_PIGMAN_SPAWN_EGG"
    ]
  },
  "membersChanged": {
    "org.bukkit.attribute.Attribute": [
      "Attribute()"
    ],
    "org.bukkit.Sound": [
      "ENTITY_ZOMBIE_PIGMAN_AMBIENT",
      "ENTITY_ZOMBIE_PIGMAN_ANGRY",
      "ENTITY_ZOMBIE_PIGMAN_DEATH",
      "ENTITY_ZOMBIE_PIGMAN_HURT",
      "MUSIC_NETHER"
    ],
    "org.bukkit.entity.EntityType": [
      "PIG_ZOMBIE"
    ],
    "org.bukkit.WorldType": [
      "BUFFET",
      "CUSTOMIZED",
      "VERSION_1_1"
    ],
    "org.bukkit.Material": [
      "ZOMBIE_PIGMAN_SPAWN_EGG"
    ]
  }
}