{
  "versionA": "1.20.4",
  "versionB": "1.20.5",
  "packagesAdded": [
    "org.bukkit.inventory.meta.components"
  ],
  "packagesRemoved": [
    "org.spigotmc.event.entity"
  ],
  "packagesChanged": [
    "com.destroystokyo.paper",
    "com.destroystokyo.paper.block",
    "com.destroystokyo.paper.entity",
    "com.destroystokyo.paper.entity.ai",
    "com.destroystokyo.paper.entity.villager",
    "com.destroystokyo.paper.event.block",
    "com.destroystokyo.paper.event.entity",
    "com.destroystokyo.paper.event.executor",
    "com.destroystokyo.paper.event.executor.asm",
    "com.destroystokyo.paper.event.inventory",
    "com.destroystokyo.paper.event.player",
    "com.destroystokyo.paper.event.profile",
    "com.destroystokyo.paper.event.server",
    "com.destroystokyo.paper.exception",
    "com.destroystokyo.paper.inventory",
    "com.destroystokyo.paper.inventory.meta",
    "com.destroystokyo.paper.loottable",
    "com.destroystokyo.paper.network",
    "com.destroystokyo.paper.profile",
    "com.destroystokyo.paper.util",
    "com.destroystokyo.paper.utils",
    "io.papermc.paper.advancement",
    "io.papermc.paper.ban",
    "io.papermc.paper.block",
    "io.papermc.paper.block.fluid",
    "io.papermc.paper.block.fluid.type",
    "io.papermc.paper.chat",
    "io.papermc.paper.command",
    "io.papermc.paper.datapack",
    "io.papermc.paper.enchantments",
    "io.papermc.paper.entity",
    "io.papermc.paper.event.block",
    "io.papermc.paper.event.entity",
    "io.papermc.paper.event.packet",
    "io.papermc.paper.event.player",
    "io.papermc.paper.event.server",
    "io.papermc.paper.event.world",
    "io.papermc.paper.event.world.border",
    "io.papermc.paper.inventory",
    "io.papermc.paper.inventory.tooltip",
    "io.papermc.paper.math",
    "io.papermc.paper.plugin",
    "io.papermc.paper.plugin.bootstrap",
    "io.papermc.paper.plugin.configuration",
    "io.papermc.paper.plugin.lifecycle.event",
    "io.papermc.paper.plugin.lifecycle.event.handler",
    "io.papermc.paper.plugin.lifecycle.event.handler.configuration",
    "io.papermc.paper.plugin.lifecycle.event.registrar",
    "io.papermc.paper.plugin.lifecycle.event.types",
    "io.papermc.paper.plugin.loader",
    "io.papermc.paper.plugin.loader.library",
    "io.papermc.paper.plugin.loader.library.impl",
    "io.papermc.paper.plugin.provider.classloader",
    "io.papermc.paper.potion",
    "io.papermc.paper.registry",
    "io.papermc.paper.registry.keys",
    "io.papermc.paper.scoreboard.numbers",
    "io.papermc.paper.tag",
    "io.papermc.paper.text",
    "io.papermc.paper.threadedregions.scheduler",
    "io.papermc.paper.util",
    "io.papermc.paper.world",
    "io.papermc.paper.world.structure",
    "org.bukkit",
    "org.bukkit.advancement",
    "org.bukkit.attribute",
    "org.bukkit.ban",
    "org.bukkit.block",
    "org.bukkit.block.banner",
    "org.bukkit.block.data",
    "org.bukkit.block.data.type",
    "org.bukkit.block.sign",
    "org.bukkit.block.spawner",
    "org.bukkit.block.structure",
    "org.bukkit.boss",
    "org.bukkit.command",
    "org.bukkit.command.defaults",
    "org.bukkit.configuration",
    "org.bukkit.configuration.file",
    "org.bukkit.configuration.serialization",
    "org.bukkit.conversations",
    "org.bukkit.damage",
    "org.bukkit.enchantments",
    "org.bukkit.entity",
    "org.bukkit.entity.memory",
    "org.bukkit.entity.minecart",
    "org.bukkit.event",
    "org.bukkit.event.block",
    "org.bukkit.event.command",
    "org.bukkit.event.enchantment",
    "org.bukkit.event.entity",
    "org.bukkit.event.hanging",
    "org.bukkit.event.inventory",
    "org.bukkit.event.player",
    "org.bukkit.event.raid",
    "org.bukkit.event.server",
    "org.bukkit.event.vehicle",
    "org.bukkit.event.weather",
    "org.bukkit.event.world",
    "org.bukkit.generator",
    "org.bukkit.generator.structure",
    "org.bukkit.help",
    "org.bukkit.inventory",
    "org.bukkit.inventory.meta",
    "org.bukkit.inventory.meta.tags",
    "org.bukkit.inventory.meta.trim",
    "org.bukkit.inventory.recipe",
    "org.bukkit.loot",
    "org.bukkit.map",
    "org.bukkit.material",
    "org.bukkit.material.types",
    "org.bukkit.metadata",
    "org.bukkit.packs",
    "org.bukkit.permissions",
    "org.bukkit.persistence",
    "org.bukkit.plugin",
    "org.bukkit.plugin.java",
    "org.bukkit.plugin.messaging",
    "org.bukkit.potion",
    "org.bukkit.profile",
    "org.bukkit.projectiles",
    "org.bukkit.scheduler",
    "org.bukkit.scoreboard",
    "org.bukkit.structure",
    "org.bukkit.util",
    "org.bukkit.util.io",
    "org.bukkit.util.noise",
    "org.bukkit.util.permissions",
    "org.spigotmc",
    "org.spigotmc.event.player"
  ],
  "classesAdded": [
    "org.bukkit.block.Vault",
    "org.bukkit.block.data.type.Vault",
    "org.bukkit.block.data.type.Vault.State",
    "org.bukkit.block.spawner.SpawnerEntry.Equipment",
    "org.bukkit.entity.AbstractWindCharge",
    "org.bukkit.entity.Armadillo",
    "org.bukkit.entity.Bogged",
    "org.bukkit.entity.BreezeWindCharge",
    "org.bukkit.entity.EntityFactory",
    "org.bukkit.entity.OminousItemSpawner",
    "org.bukkit.entity.Wolf.Variant",
    "org.bukkit.inventory.EquipmentSlotGroup",
    "org.bukkit.inventory.ItemRarity",
    "org.bukkit.inventory.meta.OminousBottleMeta",
    "org.bukkit.inventory.meta.WritableBookMeta",
    "org.bukkit.inventory.meta.components.FoodComponent",
    "org.bukkit.inventory.meta.components.FoodComponent.FoodEffect"
  ],
  "classesRemoved": [
    "com.destroystokyo.paper.Namespaced",
    "com.destroystokyo.paper.NamespacedTag",
    "org.bukkit.potion.Potion",
    "org.bukkit.potion.PotionData",
    "org.spigotmc.event.entity.EntityDismountEvent",
    "org.spigotmc.event.entity.EntityMountEvent"
  ],
  "classesChanged": [
    "com.destroystokyo.paper.entity.ai.VanillaGoal",
    "io.papermc.paper.registry.keys.TrimPatternKeys",
    "org.bukkit.Bukkit",
    "org.bukkit.Effect",
    "org.bukkit.GameRule",
    "org.bukkit.Material",
    "org.bukkit.MusicInstrument",
    "org.bukkit.Particle",
    "org.bukkit.Registry",
    "org.bukkit.Server",
    "org.bukkit.Sound",
    "org.bukkit.Tag",
    "org.bukkit.UnsafeValues",
    "org.bukkit.attribute.Attribute",
    "org.bukkit.attribute.AttributeModifier",
    "org.bukkit.block.BlockState",
    "org.bukkit.block.Conduit",
    "org.bukkit.block.banner.PatternType",
    "org.bukkit.block.data.type.TrialSpawner",
    "org.bukkit.block.spawner.SpawnerEntry",
    "org.bukkit.damage.DamageType",
    "org.bukkit.enchantments.Enchantment",
    "org.bukkit.entity.AreaEffectCloud",
    "org.bukkit.entity.Arrow",
    "org.bukkit.entity.Entity",
    "org.bukkit.entity.EntitySnapshot",
    "org.bukkit.entity.EntityType",
    "org.bukkit.entity.Player",
    "org.bukkit.entity.Skeleton.SkeletonType",
    "org.bukkit.entity.WindCharge",
    "org.bukkit.entity.Wolf",
    "org.bukkit.event.player.AsyncPlayerPreLoginEvent",
    "org.bukkit.event.player.PlayerKickEvent.Cause",
    "org.bukkit.inventory.EquipmentSlot",
    "org.bukkit.inventory.ItemFlag",
    "org.bukkit.inventory.SmithingRecipe",
    "org.bukkit.inventory.meta.BannerMeta",
    "org.bukkit.inventory.meta.BookMeta",
    "org.bukkit.inventory.meta.Damageable",
    "org.bukkit.inventory.meta.ItemMeta",
    "org.bukkit.inventory.meta.PotionMeta",
    "org.bukkit.inventory.meta.trim.TrimPattern",
    "org.bukkit.loot.LootTables",
    "org.bukkit.map.MapCursor.Type",
    "org.bukkit.plugin.PluginManager",
    "org.bukkit.plugin.SimplePluginManager",
    "org.bukkit.potion.PotionEffectType",
    "org.bukkit.potion.PotionType"
  ],
  "membersAdded": {
    "org.bukkit.inventory.ItemFlag": [
      "HIDE_ADDITIONAL_TOOLTIP",
      "HIDE_STORED_ENCHANTS"
    ],
    "org.bukkit.block.banner.PatternType": [
      "CIRCLE",
      "DIAGONAL_UP_LEFT",
      "DIAGONAL_UP_RIGHT",
      "GUSTER",
      "HALF_HORIZONTAL_BOTTOM",
      "HALF_VERTICAL_RIGHT",
      "RHOMBUS",
      "SMALL_STRIPES"
    ],
    "org.bukkit.attribute.AttributeModifier": [
      "AttributeModifier(UUID,String,double,Operation,EquipmentSlotGroup)",
      "getSlotGroup()"
    ],
    "org.bukkit.Tag": [
      "ARMADILLO_SPAWNABLE_ON",
      "BADLANDS_TERRACOTTA",
      "BLOCKS_WIND_CHARGE_EXPLOSIONS",
      "DOES_NOT_BLOCK_HOPPERS",
      "ENTITY_TYPES_AQUATIC",
      "ENTITY_TYPES_ARTHROPOD",
      "ENTITY_TYPES_DEFLECTS_PROJECTILES",
      "ENTITY_TYPES_IGNORES_POISON_AND_REGEN",
      "ENTITY_TYPES_ILLAGER",
      "ENTITY_TYPES_ILLAGER_FRIENDS",
      "ENTITY_TYPES_IMMUNE_TO_INFESTED",
      "ENTITY_TYPES_IMMUNE_TO_OOZING",
      "ENTITY_TYPES_INVERTED_HEALING_AND_HARM",
      "ENTITY_TYPES_NOT_SCARY_FOR_PUFFERFISH",
      "ENTITY_TYPES_NO_ANGER_FROM_WIND_CHARGE",
      "ENTITY_TYPES_REDIRECTABLE_PROJECTILE",
      "ENTITY_TYPES_SENSITIVE_TO_BANE_OF_ARTHROPODS",
      "ENTITY_TYPES_SENSITIVE_TO_IMPALING",
      "ENTITY_TYPES_SENSITIVE_TO_SMITE",
      "ENTITY_TYPES_WITHER_FRIENDS",
      "INCORRECT_FOR_DIAMOND_TOOL",
      "INCORRECT_FOR_GOLD_TOOL",
      "INCORRECT_FOR_IRON_TOOL",
      "INCORRECT_FOR_NETHERITE_TOOL",
      "INCORRECT_FOR_STONE_TOOL",
      "INCORRECT_FOR_WOODEN_TOOL",
      "ITEMS_ARMADILLO_FOOD",
      "ITEMS_AXOLOTL_FOOD",
      "ITEMS_BEE_FOOD",
      "ITEMS_CAMEL_FOOD",
      "ITEMS_CAT_FOOD",
      "ITEMS_CHEST_ARMOR",
      "ITEMS_CHICKEN_FOOD",
      "ITEMS_COW_FOOD",
      "ITEMS_DYEABLE",
      "ITEMS_ENCHANTABLE_ARMOR",
      "ITEMS_ENCHANTABLE_BOW",
      "ITEMS_ENCHANTABLE_CHEST_ARMOR",
      "ITEMS_ENCHANTABLE_CROSSBOW",
      "ITEMS_ENCHANTABLE_DURABILITY",
      "ITEMS_ENCHANTABLE_EQUIPPABLE",
      "ITEMS_ENCHANTABLE_FIRE_ASPECT",
      "ITEMS_ENCHANTABLE_FISHING",
      "ITEMS_ENCHANTABLE_FOOT_ARMOR",
      "ITEMS_ENCHANTABLE_HEAD_ARMOR",
      "ITEMS_ENCHANTABLE_LEG_ARMOR",
      "ITEMS_ENCHANTABLE_MACE",
      "ITEMS_ENCHANTABLE_MINING",
      "ITEMS_ENCHANTABLE_MINING_LOOT",
      "ITEMS_ENCHANTABLE_SHARP_WEAPON",
      "ITEMS_ENCHANTABLE_SWORD",
      "ITEMS_ENCHANTABLE_TRIDENT",
      "ITEMS_ENCHANTABLE_VANISHING",
      "ITEMS_ENCHANTABLE_WEAPON",
      "ITEMS_FOOT_ARMOR",
      "ITEMS_FOX_FOOD",
      "ITEMS_FROG_FOOD",
      "ITEMS_GOAT_FOOD",
      "ITEMS_HEAD_ARMOR",
      "ITEMS_HOGLIN_FOOD",
      "ITEMS_HORSE_FOOD",
      "ITEMS_HORSE_TEMPT_ITEMS",
      "ITEMS_LEG_ARMOR",
      "ITEMS_LLAMA_FOOD",
      "ITEMS_LLAMA_TEMPT_ITEMS",
      "ITEMS_MEAT",
      "ITEMS_OCELOT_FOOD",
      "ITEMS_PANDA_FOOD",
      "ITEMS_PARROT_FOOD",
      "ITEMS_PARROT_POISONOUS_FOOD",
      "ITEMS_PIGLIN_FOOD",
      "ITEMS_PIG_FOOD",
      "ITEMS_RABBIT_FOOD",
      "ITEMS_SHEEP_FOOD",
      "ITEMS_SKULLS",
      "ITEMS_STRIDER_FOOD",
      "ITEMS_STRIDER_TEMPT_ITEMS",
      "ITEMS_TURTLE_FOOD",
      "ITEMS_WOLF_FOOD"
    ],
    "org.bukkit.MusicInstrument": [
      "ADMIRE_GOAT_HORN",
      "CALL_GOAT_HORN",
      "DREAM_GOAT_HORN",
      "FEEL_GOAT_HORN",
      "PONDER_GOAT_HORN",
      "SEEK_GOAT_HORN",
      "SING_GOAT_HORN",
      "YEARN_GOAT_HORN"
    ],
    "org.bukkit.inventory.meta.ItemMeta": [
      "getEnchantmentGlintOverride()",
      "getFood()",
      "getItemName()",
      "hasEnchantmentGlintOverride()",
      "hasFood()",
      "hasItemName()",
      "hasMaxStackSize()",
      "hasRarity()",
      "isFireResistant()",
      "isHideTooltip()",
      "itemName()",
      "itemName(Component)",
      "setEnchantmentGlintOverride(Boolean)",
      "setFireResistant(boolean)",
      "setFood(FoodComponent)",
      "setHideTooltip(boolean)",
      "setItemName(String)",
      "setMaxStackSize(Integer)",
      "setRarity(ItemRarity)"
    ],
    "org.bukkit.enchantments.Enchantment": [
      "AQUA_AFFINITY",
      "BANE_OF_ARTHROPODS",
      "BLAST_PROTECTION",
      "BREACH",
      "DENSITY",
      "EFFICIENCY",
      "FEATHER_FALLING",
      "FIRE_PROTECTION",
      "FORTUNE",
      "INFINITY",
      "LOOTING",
      "LUCK_OF_THE_SEA",
      "POWER",
      "PROJECTILE_PROTECTION",
      "PROTECTION",
      "PUNCH",
      "RESPIRATION",
      "SHARPNESS",
      "SMITE",
      "UNBREAKING",
      "WIND_BURST",
      "getDamageIncrease(int,EntityType)"
    ],
    "org.bukkit.inventory.SmithingRecipe": [
      "copyDataComponents",
      "willCopyDataComponents()"
    ],
    "org.bukkit.inventory.meta.trim.TrimPattern": [
      "BOLT",
      "FLOW"
    ],
    "org.bukkit.plugin.SimplePluginManager": [
      "loadPlugins(File...)"
    ],
    "org.bukkit.inventory.EquipmentSlotGroup": [
      "EquipmentSlotGroup(String,Predicate,EquipmentSlot)",
      "MAINHAND",
      "OFFHAND",
      "example",
      "get(String,EquipmentSlot)",
      "get(String,Predicate,EquipmentSlot)",
      "predicate",
      "test(EquipmentSlot)"
    ],
    "org.bukkit.entity.Player": [
      "retrieveCookie(NamespacedKey)",
      "storeCookie(NamespacedKey,byte...)",
      "transfer(String,int)"
    ],
    "org.bukkit.inventory.meta.OminousBottleMeta": [
      "hasAmplifier()",
      "setAmplifier(int)"
    ],
    "org.bukkit.entity.Skeleton.SkeletonType": [
      "BOGGED"
    ],
    "org.bukkit.event.player.AsyncPlayerPreLoginEvent": [
      "isTransferred()",
      "AsyncPlayerPreLoginEvent(String,InetAddress,InetAddress,UUID,boolean,PlayerProfile)",
      "AsyncPlayerPreLoginEvent(String,InetAddress,UUID,boolean)",
      "AsyncPlayerPreLoginEvent(String,InetAddress,UUID,boolean,PlayerProfile)",
      "transferred"
    ],
    "com.destroystokyo.paper.entity.ai.VanillaGoal": [
      "\u003cT\u003ecreate(String,Class)"
    ],
    "org.bukkit.Effect": [
      "BEE_GROWTH",
      "SMASH_ATTACK",
      "SPAWN_COBWEB",
      "TRIAL_SPAWNER_BECOME_OMINOUS",
      "TRIAL_SPAWNER_DETECT_PLAYER_OMINOUS",
      "TRIAL_SPAWNER_SPAWN_ITEM",
      "TURTLE_EGG_PLACEMENT",
      "VAULT_ACTIVATE",
      "VAULT_DEACTIVATE",
      "VAULT_EJECT_ITEM"
    ],
    "org.bukkit.Server": [
      "getEntityFactory()",
      "isAcceptingTransfers()"
    ],
    "org.bukkit.inventory.meta.PotionMeta": [
      "hasBasePotionType()"
    ],
    "org.bukkit.entity.Wolf.Variant": [
      "ASHEN",
      "PALE",
      "RUSTY",
      "SNOWY",
      "SPOTTED",
      "STRIPED",
      "WOODS",
      "getVariant(String)"
    ],
    "org.bukkit.block.data.type.Vault": [
      "isOminous()",
      "setOminous(boolean)"
    ],
    "org.bukkit.entity.EntityFactory": [
      "createEntitySnapshot(String)"
    ],
    "org.bukkit.inventory.EquipmentSlot": [
      "BODY",
      "EquipmentSlot(Supplier)"
    ],
    "org.bukkit.Material": [
      "ARMADILLO_SCUTE",
      "ARMADILLO_SPAWN_EGG",
      "BOGGED_SPAWN_EGG",
      "BOLT_ARMOR_TRIM_SMITHING_TEMPLATE",
      "BREEZE_ROD",
      "FLOW_ARMOR_TRIM_SMITHING_TEMPLATE",
      "FLOW_BANNER_PATTERN",
      "FLOW_POTTERY_SHERD",
      "GUSTER_BANNER_PATTERN",
      "GUSTER_POTTERY_SHERD",
      "HEAVY_CORE",
      "MACE",
      "OMINOUS_BOTTLE",
      "OMINOUS_TRIAL_KEY",
      "SCRAPE_POTTERY_SHERD",
      "TURTLE_SCUTE",
      "VAULT",
      "WOLF_ARMOR"
    ],
    "org.bukkit.loot.LootTables": [
      "EQUIPMENT_TRIAL_CHAMBER",
      "EQUIPMENT_TRIAL_CHAMBER_MELEE",
      "EQUIPMENT_TRIAL_CHAMBER_RANGED",
      "OMINOUS_TRIAL_CHAMBER_CONSUMABLES",
      "OMINOUS_TRIAL_CHAMBER_KEY",
      "SHEARING_BOGGED",
      "TRIAL_CHAMBERS_REWARD_COMMON",
      "TRIAL_CHAMBERS_REWARD_OMINOUS",
      "TRIAL_CHAMBERS_REWARD_OMINOUS_COMMON",
      "TRIAL_CHAMBERS_REWARD_OMINOUS_RARE",
      "TRIAL_CHAMBERS_REWARD_OMINOUS_UNIQUE",
      "TRIAL_CHAMBERS_REWARD_RARE",
      "TRIAL_CHAMBERS_REWARD_UNIQUE",
      "TRIAL_CHAMBER_ITEMS_TO_DROP_WHEN_OMINOUS"
    ],
    "org.bukkit.block.Conduit": [
      "getFrameBlockCount()",
      "getFrameBlocks()",
      "getHuntingArea()",
      "hasTarget()",
      "isHunting()"
    ],
    "org.bukkit.inventory.ItemRarity": [
      "ItemRarity(NamedTextColor)"
    ],
    "org.bukkit.attribute.Attribute": [
      "GENERIC_FALL_DAMAGE_MULTIPLIER",
      "GENERIC_GRAVITY",
      "GENERIC_JUMP_STRENGTH",
      "GENERIC_SAFE_FALL_DISTANCE",
      "GENERIC_SCALE",
      "GENERIC_STEP_HEIGHT",
      "PLAYER_BLOCK_BREAK_SPEED",
      "PLAYER_BLOCK_INTERACTION_RANGE",
      "PLAYER_ENTITY_INTERACTION_RANGE"
    ],
    "org.bukkit.map.MapCursor.Type": [
      "BLUE_MARKER",
      "FRAME",
      "PLAYER_OFF_LIMITS",
      "PLAYER_OFF_MAP",
      "TARGET_POINT",
      "TARGET_X",
      "Type(int,String)"
    ],
    "org.bukkit.potion.PotionType": [
      "INFESTED",
      "OOZING",
      "WEAVING",
      "WIND_CHARGED",
      "HARMING",
      "HEALING",
      "LEAPING",
      "SWIFTNESS"
    ],
    "org.bukkit.block.spawner.SpawnerEntry": [
      "SpawnerEntry(EntitySnapshot,int,SpawnRule,Equipment)",
      "equipment",
      "setEquipment(Equipment)"
    ],
    "org.bukkit.Sound": [
      "BLOCK_COBWEB_BREAK",
      "BLOCK_COBWEB_FALL",
      "BLOCK_COBWEB_HIT",
      "BLOCK_COBWEB_PLACE",
      "BLOCK_COBWEB_STEP",
      "BLOCK_HEAVY_CORE_BREAK",
      "BLOCK_HEAVY_CORE_FALL",
      "BLOCK_HEAVY_CORE_HIT",
      "BLOCK_HEAVY_CORE_PLACE",
      "BLOCK_HEAVY_CORE_STEP",
      "BLOCK_TRIAL_SPAWNER_ABOUT_TO_SPAWN_ITEM",
      "BLOCK_TRIAL_SPAWNER_AMBIENT_CHARGED",
      "BLOCK_TRIAL_SPAWNER_CHARGE_ACTIVATE",
      "BLOCK_TRIAL_SPAWNER_SPAWN_ITEM",
      "BLOCK_TRIAL_SPAWNER_SPAWN_ITEM_BEGIN",
      "BLOCK_VAULT_ACTIVATE",
      "BLOCK_VAULT_AMBIENT",
      "BLOCK_VAULT_BREAK",
      "BLOCK_VAULT_CLOSE_SHUTTER",
      "BLOCK_VAULT_DEACTIVATE",
      "BLOCK_VAULT_EJECT_ITEM",
      "BLOCK_VAULT_FALL",
      "BLOCK_VAULT_HIT",
      "BLOCK_VAULT_INSERT_ITEM",
      "BLOCK_VAULT_INSERT_ITEM_FAIL",
      "BLOCK_VAULT_OPEN_SHUTTER",
      "BLOCK_VAULT_PLACE",
      "BLOCK_VAULT_STEP",
      "BLOCK_WET_SPONGE_DRIES",
      "ENTITY_ARMADILLO_AMBIENT",
      "ENTITY_ARMADILLO_BRUSH",
      "ENTITY_ARMADILLO_DEATH",
      "ENTITY_ARMADILLO_EAT",
      "ENTITY_ARMADILLO_HURT",
      "ENTITY_ARMADILLO_HURT_REDUCED",
      "ENTITY_ARMADILLO_LAND",
      "ENTITY_ARMADILLO_PEEK",
      "ENTITY_ARMADILLO_ROLL",
      "ENTITY_ARMADILLO_SCUTE_DROP",
      "ENTITY_ARMADILLO_STEP",
      "ENTITY_ARMADILLO_UNROLL_FINISH",
      "ENTITY_ARMADILLO_UNROLL_START",
      "ENTITY_BOGGED_AMBIENT",
      "ENTITY_BOGGED_DEATH",
      "ENTITY_BOGGED_HURT",
      "ENTITY_BOGGED_SHEAR",
      "ENTITY_BOGGED_STEP",
      "ENTITY_BREEZE_CHARGE",
      "ENTITY_BREEZE_DEFLECT",
      "ENTITY_BREEZE_WHIRL",
      "ENTITY_BREEZE_WIND_BURST",
      "ENTITY_DONKEY_JUMP",
      "ENTITY_MULE_JUMP",
      "ENTITY_PARROT_IMITATE_BOGGED",
      "ENTITY_WIND_CHARGE_THROW",
      "ENTITY_WIND_CHARGE_WIND_BURST",
      "EVENT_MOB_EFFECT_BAD_OMEN",
      "EVENT_MOB_EFFECT_RAID_OMEN",
      "EVENT_MOB_EFFECT_TRIAL_OMEN",
      "ITEM_ARMOR_EQUIP_WOLF",
      "ITEM_ARMOR_UNEQUIP_WOLF",
      "ITEM_MACE_SMASH_AIR",
      "ITEM_MACE_SMASH_GROUND",
      "ITEM_MACE_SMASH_GROUND_HEAVY",
      "ITEM_OMINOUS_BOTTLE_DISPOSE",
      "ITEM_WOLF_ARMOR_BREAK",
      "ITEM_WOLF_ARMOR_CRACK",
      "ITEM_WOLF_ARMOR_DAMAGE",
      "ITEM_WOLF_ARMOR_REPAIR"
    ],
    "org.bukkit.entity.EntityType": [
      "ARMADILLO",
      "BREEZE_WIND_CHARGE",
      "EYE_OF_ENDER",
      "FISHING_BOBBER",
      "LEASH_KNOT",
      "OMINOUS_ITEM_SPAWNER",
      "SPAWNER_MINECART"
    ],
    "org.bukkit.inventory.meta.components.FoodComponent": [
      "addEffect(PotionEffect,float)",
      "canAlwaysEat()",
      "getEatSeconds()",
      "getNutrition()",
      "setCanAlwaysEat(boolean)",
      "setEatSeconds(float)",
      "setEffects(List)",
      "setNutrition(int)"
    ],
    "org.bukkit.event.player.PlayerKickEvent.Cause": [
      "INVALID_COOKIE"
    ],
    "org.bukkit.block.data.type.Vault.State": [
      "EJECTING",
      "UNLOCKING"
    ],
    "org.bukkit.Particle": [
      "ANGRY_VILLAGER",
      "BUBBLE",
      "DRIPPING_LAVA",
      "DRIPPING_WATER",
      "DUST",
      "DUST_PILLAR",
      "ENCHANT",
      "ENCHANTED_HIT",
      "ENTITY_EFFECT",
      "EXPLOSION_EMITTER",
      "GUST_EMITTER_LARGE",
      "GUST_EMITTER_SMALL",
      "HAPPY_VILLAGER",
      "INSTANT_EFFECT",
      "ITEM_COBWEB",
      "ITEM_SLIME",
      "ITEM_SNOWBALL",
      "LARGE_SMOKE",
      "OMINOUS_SPAWNING",
      "POOF",
      "RAIN",
      "SMALL_GUST",
      "TRIAL_SPAWNER_DETECTION_OMINOUS",
      "UNDERWATER",
      "VAULT_CONNECTION"
    ],
    "org.bukkit.inventory.meta.Damageable": [
      "hasMaxDamage()",
      "setMaxDamage(Integer)"
    ],
    "org.bukkit.entity.OminousItemSpawner": [
      "getSpawnItemAfterTicks()",
      "setSpawnItemAfterTicks(long)"
    ],
    "org.bukkit.inventory.meta.components.FoodComponent.FoodEffect": [
      "getProbability()",
      "setProbability(float)"
    ],
    "org.bukkit.block.spawner.SpawnerEntry.Equipment": [
      "Equipment(LootTable,Map)",
      "dropChances",
      "equipmentLootTable",
      "getDropChances()",
      "getEquipmentLootTable()",
      "setEquipmentLootTable(LootTable)"
    ],
    "org.bukkit.potion.PotionEffectType": [
      "RAID_OMEN",
      "TRIAL_OMEN",
      "HASTE",
      "INSTANT_HEALTH",
      "JUMP_BOOST",
      "MINING_FATIGUE",
      "NAUSEA"
    ],
    "org.bukkit.Registry": [
      "WOLF_VARIANT"
    ],
    "org.bukkit.GameRule": [
      "SPAWN_CHUNK_RADIUS"
    ]
  },
  "membersRemoved": {
    "org.bukkit.inventory.ItemFlag": [
      "HIDE_POTION_EFFECTS"
    ],
    "org.bukkit.block.banner.PatternType": [
      "CIRCLE_MIDDLE",
      "DIAGONAL_LEFT_MIRROR",
      "DIAGONAL_RIGHT_MIRROR",
      "HALF_HORIZONTAL_MIRROR",
      "HALF_VERTICAL_MIRROR",
      "RHOMBUS_MIDDLE",
      "STRIPE_SMALL"
    ],
    "org.bukkit.attribute.Attribute": [
      "HORSE_JUMP_STRENGTH"
    ],
    "org.bukkit.Tag": [
      "ENTITY_TYPES_DEFLECTS_TRIDENTS"
    ],
    "org.bukkit.MusicInstrument": [
      "ADMIRE",
      "CALL",
      "DREAM",
      "FEEL",
      "PONDER",
      "SEEK",
      "SING",
      "YEARN"
    ],
    "org.bukkit.map.MapCursor.Type": [
      "BLUE_POINTER",
      "DESERT_VILLAGE",
      "GREEN_POINTER",
      "PLAINS_VILLAGE",
      "RED_POINTER",
      "SAVANNA_VILLAGE",
      "SMALL_WHITE_CIRCLE",
      "SNOWY_VILLAGE",
      "TAIGA_VILLAGE",
      "TEMPLE",
      "WHITE_CIRCLE",
      "WHITE_CROSS",
      "WHITE_POINTER"
    ],
    "org.bukkit.inventory.meta.ItemMeta": [
      "getCanDestroy()",
      "getCanPlaceOn()",
      "getDestroyableKeys()",
      "getPlaceableKeys()",
      "hasDestroyableKeys()",
      "hasPlaceableKeys()",
      "setCanDestroy(Set)",
      "setCanPlaceOn(Set)",
      "setDestroyableKeys(Collection)",
      "setPlaceableKeys(Collection)"
    ],
    "org.bukkit.enchantments.Enchantment": [
      "ARROW_DAMAGE",
      "ARROW_FIRE",
      "ARROW_INFINITE",
      "ARROW_KNOCKBACK",
      "DAMAGE_ALL",
      "DAMAGE_ARTHROPODS",
      "DAMAGE_UNDEAD",
      "DIG_SPEED",
      "DURABILITY",
      "LOOT_BONUS_BLOCKS",
      "LOOT_BONUS_MOBS",
      "OXYGEN",
      "PROTECTION_ENVIRONMENTAL",
      "PROTECTION_EXPLOSIONS",
      "PROTECTION_FALL",
      "PROTECTION_FIRE",
      "PROTECTION_PROJECTILE",
      "WATER_WORKER"
    ],
    "org.bukkit.potion.PotionType": [
      "INSTANT_HEAL",
      "UNCRAFTABLE"
    ],
    "org.bukkit.inventory.SmithingRecipe": [
      "copyNbt"
    ],
    "org.bukkit.Sound": [
      "ENTITY_GENERIC_WIND_BURST"
    ],
    "org.bukkit.entity.EntityType": [
      "DROPPED_ITEM",
      "FISHING_HOOK",
      "LEASH_HITCH",
      "MINECART_CHEST",
      "MINECART_COMMAND",
      "MINECART_FURNACE",
      "MINECART_HOPPER",
      "MINECART_MOB_SPAWNER",
      "MINECART_TNT",
      "MUSHROOM_COW",
      "PRIMED_TNT",
      "SNOWMAN",
      "THROWN_EXP_BOTTLE"
    ],
    "org.bukkit.potion.PotionData": [
      "extended",
      "PotionData(PotionType)",
      "PotionData(PotionType,boolean,boolean)",
      "isUpgraded()",
      "upgraded"
    ],
    "org.bukkit.event.player.AsyncPlayerPreLoginEvent": [
      "AsyncPlayerPreLoginEvent(String,InetAddress,InetAddress,UUID,PlayerProfile)",
      "AsyncPlayerPreLoginEvent(String,InetAddress,InetAddress,UUID,PlayerProfile,String)",
      "AsyncPlayerPreLoginEvent(String,InetAddress,UUID,PlayerProfile)"
    ],
    "org.bukkit.Particle": [
      "BLOCK_CRACK",
      "BLOCK_DUST",
      "CRIT_MAGIC",
      "DRIP_LAVA",
      "DRIP_WATER",
      "ENCHANTMENT_TABLE",
      "EXPLOSION_HUGE",
      "EXPLOSION_LARGE",
      "EXPLOSION_NORMAL",
      "FIREWORKS_SPARK",
      "GUST_EMITTER",
      "ITEM_CRACK",
      "LEGACY_BLOCK_CRACK",
      "LEGACY_BLOCK_DUST",
      "LEGACY_FALLING_DUST",
      "MOB_APPEARANCE",
      "SMOKE_LARGE",
      "SMOKE_NORMAL",
      "SNOW_SHOVEL",
      "SPELL_INSTANT",
      "SPELL_MOB",
      "SPELL_MOB_AMBIENT",
      "SPELL_WITCH",
      "SUSPENDED",
      "SUSPENDED_DEPTH",
      "TOWN_AURA",
      "WATER_BUBBLE",
      "WATER_DROP",
      "WATER_SPLASH",
      "WATER_WAKE"
    ],
    "com.destroystokyo.paper.entity.ai.VanillaGoal": [
      "create(String,Class)"
    ],
    "org.bukkit.UnsafeValues": [
      "getItemAttributes(Material,EquipmentSlot)",
      "getItemRarity(Material)",
      "getItemStackRarity(ItemStack)"
    ],
    "org.bukkit.potion.Potion": [
      "EXTENDED_BIT",
      "POTION_BIT",
      "Potion(PotionType)",
      "Potion(PotionType,int)",
      "Potion(PotionType,int,boolean)",
      "Potion(PotionType,int,boolean,boolean)",
      "SPLASH_BIT",
      "TIER_BIT",
      "TIER_SHIFT",
      "apply(ItemStack)",
      "brewer",
      "extend()",
      "fromDamage(int)",
      "fromItemStack(ItemStack)",
      "getBrewer()",
      "getNameId()",
      "hasExtendedDuration()",
      "isSplash()",
      "setHasExtendedDuration(boolean)",
      "setPotionBrewer(PotionBrewer)",
      "setSplash(boolean)",
      "setType(PotionType)",
      "splash",
      "toDamageValue()"
    ],
    "org.bukkit.inventory.meta.PotionMeta": [
      "getBasePotionData()",
      "setBasePotionData(PotionData)"
    ],
    "com.destroystokyo.paper.NamespacedTag": [
      "NamespacedTag(Plugin,String)",
      "NamespacedTag(String,String)",
      "VALID_KEY",
      "VALID_NAMESPACE",
      "randomKey()"
    ],
    "org.bukkit.inventory.EquipmentSlot": [
      "EquipmentSlot()"
    ],
    "org.bukkit.potion.PotionEffectType": [
      "convertLegacy(String)",
      "CONFUSION",
      "DAMAGE_RESISTANCE",
      "FAST_DIGGING",
      "HARM",
      "HEAL",
      "INCREASE_DAMAGE",
      "SLOW",
      "SLOW_DIGGING"
    ],
    "org.bukkit.Material": [
      "SCUTE"
    ]
  },
  "membersChanged": {
    "org.bukkit.inventory.ItemFlag": [
      "HIDE_POTION_EFFECTS"
    ],
    "org.bukkit.block.banner.PatternType": [
      "CIRCLE_MIDDLE",
      "DIAGONAL_LEFT_MIRROR",
      "DIAGONAL_RIGHT_MIRROR",
      "HALF_HORIZONTAL_MIRROR",
      "HALF_VERTICAL_MIRROR",
      "RHOMBUS_MIDDLE",
      "STRIPE_SMALL"
    ],
    "org.bukkit.attribute.Attribute": [
      "HORSE_JUMP_STRENGTH"
    ],
    "org.bukkit.Tag": [
      "ENTITY_TYPES_DEFLECTS_TRIDENTS"
    ],
    "org.bukkit.MusicInstrument": [
      "ADMIRE",
      "CALL",
      "DREAM",
      "FEEL",
      "PONDER",
      "SEEK",
      "SING",
      "YEARN"
    ],
    "org.bukkit.map.MapCursor.Type": [
      "BLUE_POINTER",
      "DESERT_VILLAGE",
      "GREEN_POINTER",
      "PLAINS_VILLAGE",
      "RED_POINTER",
      "SAVANNA_VILLAGE",
      "SMALL_WHITE_CIRCLE",
      "SNOWY_VILLAGE",
      "TAIGA_VILLAGE",
      "TEMPLE",
      "WHITE_CIRCLE",
      "WHITE_CROSS",
      "WHITE_POINTER"
    ],
    "org.bukkit.inventory.meta.ItemMeta": [
      "getCanDestroy()",
      "getCanPlaceOn()",
      "getDestroyableKeys()",
      "getPlaceableKeys()",
      "hasDestroyableKeys()",
      "hasPlaceableKeys()",
      "setCanDestroy(Set)",
      "setCanPlaceOn(Set)",
      "setDestroyableKeys(Collection)",
      "setPlaceableKeys(Collection)"
    ],
    "org.bukkit.enchantments.Enchantment": [
      "ARROW_DAMAGE",
      "ARROW_FIRE",
      "ARROW_INFINITE",
      "ARROW_KNOCKBACK",
      "DAMAGE_ALL",
      "DAMAGE_ARTHROPODS",
      "DAMAGE_UNDEAD",
      "DIG_SPEED",
      "DURABILITY",
      "LOOT_BONUS_BLOCKS",
      "LOOT_BONUS_MOBS",
      "OXYGEN",
      "PROTECTION_ENVIRONMENTAL",
      "PROTECTION_EXPLOSIONS",
      "PROTECTION_FALL",
      "PROTECTION_FIRE",
      "PROTECTION_PROJECTILE",
      "WATER_WORKER"
    ],
    "org.bukkit.potion.PotionType": [
      "INSTANT_HEAL",
      "UNCRAFTABLE"
    ],
    "org.bukkit.inventory.SmithingRecipe": [
      "copyNbt"
    ],
    "org.bukkit.Sound": [
      "ENTITY_GENERIC_WIND_BURST"
    ],
    "org.bukkit.entity.EntityType": [
      "DROPPED_ITEM",
      "FISHING_HOOK",
      "LEASH_HITCH",
      "MINECART_CHEST",
      "MINECART_COMMAND",
      "MINECART_FURNACE",
      "MINECART_HOPPER",
      "MINECART_MOB_SPAWNER",
      "MINECART_TNT",
      "MUSHROOM_COW",
      "PRIMED_TNT",
      "SNOWMAN",
      "THROWN_EXP_BOTTLE"
    ],
    "org.bukkit.potion.PotionData": [
      "extended",
      "PotionData(PotionType)",
      "PotionData(PotionType,boolean,boolean)",
      "isUpgraded()",
      "upgraded"
    ],
    "org.bukkit.event.player.AsyncPlayerPreLoginEvent": [
      "AsyncPlayerPreLoginEvent(String,InetAddress,InetAddress,UUID,PlayerProfile)",
      "AsyncPlayerPreLoginEvent(String,InetAddress,InetAddress,UUID,PlayerProfile,String)",
      "AsyncPlayerPreLoginEvent(String,InetAddress,UUID,PlayerProfile)"
    ],
    "org.bukkit.Particle": [
      "BLOCK_CRACK",
      "BLOCK_DUST",
      "CRIT_MAGIC",
      "DRIP_LAVA",
      "DRIP_WATER",
      "ENCHANTMENT_TABLE",
      "EXPLOSION_HUGE",
      "EXPLOSION_LARGE",
      "EXPLOSION_NORMAL",
      "FIREWORKS_SPARK",
      "GUST_EMITTER",
      "ITEM_CRACK",
      "LEGACY_BLOCK_CRACK",
      "LEGACY_BLOCK_DUST",
      "LEGACY_FALLING_DUST",
      "MOB_APPEARANCE",
      "SMOKE_LARGE",
      "SMOKE_NORMAL",
      "SNOW_SHOVEL",
      "SPELL_INSTANT",
      "SPELL_MOB",
      "SPELL_MOB_AMBIENT",
      "SPELL_WITCH",
      "SUSPENDED",
      "SUSPENDED_DEPTH",
      "TOWN_AURA",
      "WATER_BUBBLE",
      "WATER_DROP",
      "WATER_SPLASH",
      "WATER_WAKE"
    ],
    "com.destroystokyo.paper.entity.ai.VanillaGoal": [
      "create(String,Class)"
    ],
    "org.bukkit.UnsafeValues": [
      "getItemAttributes(Material,EquipmentSlot)",
      "getItemRarity(Material)",
      "getItemStackRarity(ItemStack)"
    ],
    "org.bukkit.potion.Potion": [
      "EXTENDED_BIT",
      "POTION_BIT",
      "Potion(PotionType)",
      "Potion(PotionType,int)",
      "Potion(PotionType,int,boolean)",
      "Potion(PotionType,int,boolean,boolean)",
      "SPLASH_BIT",
      "TIER_BIT",
      "TIER_SHIFT",
      "apply(ItemStack)",
      "brewer",
      "extend()",
      "fromDamage(int)",
      "fromItemStack(ItemStack)",
      "getBrewer()",
      "getNameId()",
      "hasExtendedDuration()",
      "isSplash()",
      "setHasExtendedDuration(boolean)",
      "setPotionBrewer(PotionBrewer)",
      "setSplash(boolean)",
      "setType(PotionType)",
      "splash",
      "toDamageValue()"
    ],
    "org.bukkit.inventory.meta.PotionMeta": [
      "getBasePotionData()",
      "setBasePotionData(PotionData)"
    ],
    "com.destroystokyo.paper.NamespacedTag": [
      "NamespacedTag(Plugin,String)",
      "NamespacedTag(String,String)",
      "VALID_KEY",
      "VALID_NAMESPACE",
      "randomKey()"
    ],
    "org.bukkit.inventory.EquipmentSlot": [
      "EquipmentSlot()"
    ],
    "org.bukkit.potion.PotionEffectType": [
      "convertLegacy(String)",
      "CONFUSION",
      "DAMAGE_RESISTANCE",
      "FAST_DIGGING",
      "HARM",
      "HEAL",
      "INCREASE_DAMAGE",
      "SLOW",
      "SLOW_DIGGING"
    ],
    "org.bukkit.Material": [
      "SCUTE"
    ]
  }
}